Workbook

Sheet Atlas
B2: The Decomposition Atlas — wave-66
B4: field | C4: value
B5: What this is | C5: Every sibling work pushed to SuperInstance (and the external research it leaned on), decomposed into elementary parts as spreadsheet logic.
B6: Method | C6: 5 canonical layers (substrate/mechanism/policy/interface/evidence); each part carries a gate, a failure mode, and file:line evidence; jevs swept the gates (soft emits; observation only at holes).
B7: Corpus | C7: 29 works across 6 families (substrate, garden, swarm, organ, labs, meta)
B8: Elementary parts | C8: 528
B9: Gated parts | C9: 401 (75.9%)
B10: Gate holes (observed) | C10: 127
B11: Gate kinds | C11: invariant:100, postcondition:87, admission:67, seal:52, precondition:50, budget:25, conservation:20
B12: Sweep field | C12: exoj policy=ledger, deformations=474, observations=130, prob_open=0.14
B13: Chain of record | C13: 606 links, verify ok=True, tip 13463fd02be3ac4f…
B14: Doctrine | C14: Elementary = cannot be split further without changing meaning. Decision rules before the run. Honest negatives are crown jewels. Ledgers append-only.
B17: The five layers of logic
B18: 0 | C18: substrate | D18: what irreducible representation does the work stand on?
B19: 1 | C19: mechanism | D19: what transforms state, and from what to what?
B20: 2 | C20: policy | D20: what decides, admits, prices, or refuses?
B21: 3 | C21: interface | D21: what does the outside touch (wires, tools, sheets)?
B22: 4 | C22: evidence | D22: what proves it ran, and what makes tampering loud?

Sheet Corpus
B2: Corpus — the studied works
B4: work | C4: family | D4: repo_path | E4: head | F4: smoke_verdict | G4: smoke_notes | H4: essence | I4: parts | J4: gates | K4: holes | L4: L0 | M4: L1 | N4: L2 | O4: L3 | P4: L4 | Q4: ideas | R4: prob_open
B5: qthe | C5: substrate | D5: /home/z/my-project/qthe | E5: 6017f80 | F5: PASS 54/54 | G5: Repo's own negative-control selftest: 54 cases, 0 escapes (S1 tamper sweep 49/49, S2-S6 fail-closed). Cheapest runnable in-repo suite. Honest negatives: (1) the | H5: One-byte ternary hyper-embedding: 6-bit spatial amplitude + 2-bit timbre, integer-exact kernel with wormhole mechanics and pre-registered gates. | I5: =COUNTIF(Parts!B5:B532,B5) -> 22 | J5: =COUNTIFS(Parts!B5:B532,B5,Parts!K5:K532,"<>") -> 21 | K5: =I5-J5 -> 1 | L5: =COUNTIFS(Parts!B5:B532,B5,Parts!E5:E532,0) -> 4 | M5: =COUNTIFS(Parts!B5:B532,B5,Parts!E5:E532,1) -> 9 | N5: =COUNTIFS(Parts!B5:B532,B5,Parts!E5:E532,2) -> 3 | O5: =COUNTIFS(Parts!B5:B532,B5,Parts!E5:E532,3) -> 2 | P5: =COUNTIFS(Parts!B5:B532,B5,Parts!E5:E532,4) -> 4 | R5: 0.1226
B6: quilt-jepa | C6: substrate | D6: /home/z/my-project/quilt-jepa | E6: a47762a | F6: PASS (chain + seals) | G6: Repo's own fail-closed verifier, read-only: 'OK chain 7 rows, tip 09e84771c690..., claims 3/6, registration seal verified' exit 0. Honest negatives: (1) `node r | H6: Tiny JEPA world model in a cell mesh: per-cell latents, EMA targets, conservation-law surprise diffusion, ten rounds of pre-registered claims. | I6: =COUNTIF(Parts!B5:B532,B6) -> 18 | J6: =COUNTIFS(Parts!B5:B532,B6,Parts!K5:K532,"<>") -> 15 | K6: =I6-J6 -> 3 | L6: =COUNTIFS(Parts!B5:B532,B6,Parts!E5:E532,0) -> 4 | M6: =COUNTIFS(Parts!B5:B532,B6,Parts!E5:E532,1) -> 7 | N6: =COUNTIFS(Parts!B5:B532,B6,Parts!E5:E532,2) -> 2 | O6: =COUNTIFS(Parts!B5:B532,B6,Parts!E5:E532,3) -> 1 | P6: =COUNTIFS(Parts!B5:B532,B6,Parts!E5:E532,4) -> 4 | R6: 0.1308
B7: jev-quilt | C7: substrate | D7: /home/z/my-project/jev-quilt | E7: 30e431b | F7: PASS 249 ran, 0 failures (6 skipped, 2 expected failures) in 38.5s | G7: Full suite measured live (README's '81 passed, 3 skipped' is stale — the suite has grown; suite status is MEASURED not written, exactly as the README demands). | H7: Cellular-first decision substrate: typed decision-surface cells, delta hooks with deadband floors, per-cell append-only bookkeeper, exact Q16 rationals. | I7: =COUNTIF(Parts!B5:B532,B7) -> 20 | J7: =COUNTIFS(Parts!B5:B532,B7,Parts!K5:K532,"<>") -> 18 | K7: =I7-J7 -> 2 | L7: =COUNTIFS(Parts!B5:B532,B7,Parts!E5:E532,0) -> 4 | M7: =COUNTIFS(Parts!B5:B532,B7,Parts!E5:E532,1) -> 4 | N7: =COUNTIFS(Parts!B5:B532,B7,Parts!E5:E532,2) -> 7 | O7: =COUNTIFS(Parts!B5:B532,B7,Parts!E5:E532,3) -> 2 | P7: =COUNTIFS(Parts!B5:B532,B7,Parts!E5:E532,4) -> 3 | R7: 0.1132
B8: quilt-qcells | C8: substrate | D8: /home/z/my-project/quilt-qcells | E8: 615ddcf | F8: PASS — ALL GREEN, P1-P4 (16 circuits, 1418 rows, 4254/4254 tamper localized, 5/5 negatives, 6.4s) | G8: Run in a /tmp scratch copy (cp -rp) because the task forbids modifying the studied repo and a conformance run writes receipts. Honest negative found: the commit | H8: Quantum ops as quilt cells: the fnv1a-64 hash-chain ledger IS the circuit — 7 opcodes, replay equals oracle, single-byte tamper localization, out-of-band anchors. | I8: =COUNTIF(Parts!B5:B532,B8) -> 21 | J8: =COUNTIFS(Parts!B5:B532,B8,Parts!K5:K532,"<>") -> 20 | K8: =I8-J8 -> 1 | L8: =COUNTIFS(Parts!B5:B532,B8,Parts!E5:E532,0) -> 4 | M8: =COUNTIFS(Parts!B5:B532,B8,Parts!E5:E532,1) -> 4 | N8: =COUNTIFS(Parts!B5:B532,B8,Parts!E5:E532,2) -> 4 | O8: =COUNTIFS(Parts!B5:B532,B8,Parts!E5:E532,3) -> 3 | P8: =COUNTIFS(Parts!B5:B532,B8,Parts!E5:E532,4) -> 6 | R8: 0.137
B9: jev-garden | C9: garden | D9: /home/z/my-project/jev-garden | E9: d05e1d9 | F9: PASS 30/30 | G9: Second verdict: node smoke.mjs -> PASS 9/9 (exit 0). Both offline, no API key, <5s. teacher.mjs (the only networked module) is never invoked by tests; selftest | H9: living JEV: rhizome+parametric head, watch-deform-observe-idle-compile-serve, sealed promotion gate | I9: =COUNTIF(Parts!B5:B532,B9) -> 26 | J9: =COUNTIFS(Parts!B5:B532,B9,Parts!K5:K532,"<>") -> 26 | K9: =I9-J9 -> 0 | L9: =COUNTIFS(Parts!B5:B532,B9,Parts!E5:E532,0) -> 2 | M9: =COUNTIFS(Parts!B5:B532,B9,Parts!E5:E532,1) -> 10 | N9: =COUNTIFS(Parts!B5:B532,B9,Parts!E5:E532,2) -> 5 | O9: =COUNTIFS(Parts!B5:B532,B9,Parts!E5:E532,3) -> 6 | P9: =COUNTIFS(Parts!B5:B532,B9,Parts!E5:E532,4) -> 3 | R9: 0.7996
B10: jeviter | C10: garden | D10: /home/z/my-project/jeviter | E10: b8c5801 | F10: PASS 85/85 | G10: node --test auto-discovery, 0.7s, offline, zero deps. Additional dog-food: node examples/vibe-distill.js --check -> '[distill] --check re-verify: PASS' (3 pinne | H10: homeostatic iteration: rest-and-react on surprise, every silence receipted, living threshold ratchets | I10: =COUNTIF(Parts!B5:B532,B10) -> 24 | J10: =COUNTIFS(Parts!B5:B532,B10,Parts!K5:K532,"<>") -> 24 | K10: =I10-J10 -> 0 | L10: =COUNTIFS(Parts!B5:B532,B10,Parts!E5:E532,0) -> 2 | M10: =COUNTIFS(Parts!B5:B532,B10,Parts!E5:E532,1) -> 8 | N10: =COUNTIFS(Parts!B5:B532,B10,Parts!E5:E532,2) -> 7 | O10: =COUNTIFS(Parts!B5:B532,B10,Parts!E5:E532,3) -> 2 | P10: =COUNTIFS(Parts!B5:B532,B10,Parts!E5:E532,4) -> 5 | R10: 0.8523
B11: exoj | C11: garden | D11: /home/z/my-project/exoj | E11: a34ab8d | F11: PASS 3/3 | G11: Seedbox-inherited smoke (sha256 KAT, randomBytes, charter present), <1s, offline. Stronger second verdict: node experiments/e_x0_pocs.mjs -> EX0 VERDICT 8/8 PAS | H11: field is primary: non-collapsing hex-lattice scratch-paper, soft JEV writes, recorded observation, content-addressed proof | I11: =COUNTIF(Parts!B5:B532,B11) -> 26 | J11: =COUNTIFS(Parts!B5:B532,B11,Parts!K5:K532,"<>") -> 24 | K11: =I11-J11 -> 2 | L11: =COUNTIFS(Parts!B5:B532,B11,Parts!E5:E532,0) -> 4 | M11: =COUNTIFS(Parts!B5:B532,B11,Parts!E5:E532,1) -> 10 | N11: =COUNTIFS(Parts!B5:B532,B11,Parts!E5:E532,2) -> 4 | O11: =COUNTIFS(Parts!B5:B532,B11,Parts!E5:E532,3) -> 5 | P11: =COUNTIFS(Parts!B5:B532,B11,Parts!E5:E532,4) -> 3 | R11: 0.631
B12: fleet-seeds | C12: garden | D12: /home/z/my-project/fleet-seeds | E12: 8d875df | F12: PASS (1 commit, SMOKE OK 3/3, tree clean after cleanup) | G12: The offline mode exists: --selftest spawns a demo repo in .selftest/ (git init + first commit, no network), runs its smoke.mjs (3/3 green), then removes everyth | H12: the seedbox: seed.md -> rigor-at-birth repo whose first commit is charter law | I12: =COUNTIF(Parts!B5:B532,B12) -> 16 | J12: =COUNTIFS(Parts!B5:B532,B12,Parts!K5:K532,"<>") -> 15 | K12: =I12-J12 -> 1 | L12: =COUNTIFS(Parts!B5:B532,B12,Parts!E5:E532,0) -> 0 | M12: =COUNTIFS(Parts!B5:B532,B12,Parts!E5:E532,1) -> 1 | N12: =COUNTIFS(Parts!B5:B532,B12,Parts!E5:E532,2) -> 4 | O12: =COUNTIFS(Parts!B5:B532,B12,Parts!E5:E532,3) -> 4 | P12: =COUNTIFS(Parts!B5:B532,B12,Parts!E5:E532,4) -> 7 | R12: 0.6883
B13: quilt-murmur | C13: swarm | D13: /home/z/my-project/download/quilt-murmur | E13: 2a38044 | F13: SMOKE OK — 16/16 checks pass | G13: Offline, no API keys (MothVault degrades to labeled mock), <1s wall. Checks: engine reflex self-write, bus pool in (0,1) + zero-trust zero-influence, hedge lead | H13: Gossip trust economy: envelope + log-odds pooling, Hedge trust, provenance/admission gates, evolutionary gardener — every claim receipted | I13: =COUNTIF(Parts!B5:B532,B13) -> 28 | J13: =COUNTIFS(Parts!B5:B532,B13,Parts!K5:K532,"<>") -> 23 | K13: =I13-J13 -> 5 | L13: =COUNTIFS(Parts!B5:B532,B13,Parts!E5:E532,0) -> 3 | M13: =COUNTIFS(Parts!B5:B532,B13,Parts!E5:E532,1) -> 15 | N13: =COUNTIFS(Parts!B5:B532,B13,Parts!E5:E532,2) -> 6 | O13: =COUNTIFS(Parts!B5:B532,B13,Parts!E5:E532,3) -> 1 | P13: =COUNTIFS(Parts!B5:B532,B13,Parts!E5:E532,4) -> 3 | R13: 0.1372
B14: quilt-pincher | C14: swarm | D14: /home/z/my-project/quilt-pincher | E14: 15fcd53 | F14: 12/12 tests pass, 0 fail (5.2s, offline) | G14: node:test runner via tsx; covers direct-hit tier, confirm tier, compile tier (mock compiler), veto paths, confidence climb, PincherSheet composition, and the th | H14: Reflex engine built entirely from quilt cells: pinch, match, veto, execute — three latency tiers, LLM only as compiler | I14: =COUNTIF(Parts!B5:B532,B14) -> 18 | J14: =COUNTIFS(Parts!B5:B532,B14,Parts!K5:K532,"<>") -> 10 | K14: =I14-J14 -> 8 | L14: =COUNTIFS(Parts!B5:B532,B14,Parts!E5:E532,0) -> 3 | M14: =COUNTIFS(Parts!B5:B532,B14,Parts!E5:E532,1) -> 7 | N14: =COUNTIFS(Parts!B5:B532,B14,Parts!E5:E532,2) -> 3 | O14: =COUNTIFS(Parts!B5:B532,B14,Parts!E5:E532,3) -> 3 | P14: =COUNTIFS(Parts!B5:B532,B14,Parts!E5:E532,4) -> 2 | R14: 0.14
B15: crab-traps | C15: swarm | D15: /home/z/my-project/crab-traps | E15: 37c34bb | F15: 12/12 controls PASS, fail-closed (0.18s, stdlib-only, zero network) | G15: Negative controls T1-T8 (tampered stone bytes, wrong pins, flipped witness/artifact/prediction/fixture bytes, skipped middle receipt) each -> DISAGREE; POS unta | H15: Lures put foreign bots to work; canonical-JSON hash chains, consent plaque and honest economy make every catch and every tamper loud | I15: =COUNTIF(Parts!B5:B532,B15) -> 22 | J15: =COUNTIFS(Parts!B5:B532,B15,Parts!K5:K532,"<>") -> 16 | K15: =I15-J15 -> 6 | L15: =COUNTIFS(Parts!B5:B532,B15,Parts!E5:E532,0) -> 4 | M15: =COUNTIFS(Parts!B5:B532,B15,Parts!E5:E532,1) -> 8 | N15: =COUNTIFS(Parts!B5:B532,B15,Parts!E5:E532,2) -> 6 | O15: =COUNTIFS(Parts!B5:B532,B15,Parts!E5:E532,3) -> 2 | P15: =COUNTIFS(Parts!B5:B532,B15,Parts!E5:E532,4) -> 2 | R15: 0.1329
B16: quilt-organ-workers | C16: organ | D16: /home/z/my-project/quilt-organ-workers | E16: 45f4768 | F16: NOT_RUN | G16: Reason: CF worker requires deploy — scripts/deploy.sh authenticates to the Cloudflare REST API (token verify, KV namespace, script upload, cron schedules) and t | H16: Three Cloudflare workers: content-addressed organ store, independent drift watcher, judge relay. | I16: =COUNTIF(Parts!B5:B532,B16) -> 20 | J16: =COUNTIFS(Parts!B5:B532,B16,Parts!K5:K532,"<>") -> 19 | K16: =I16-J16 -> 1 | L16: =COUNTIFS(Parts!B5:B532,B16,Parts!E5:E532,0) -> 3 | M16: =COUNTIFS(Parts!B5:B532,B16,Parts!E5:E532,1) -> 4 | N16: =COUNTIFS(Parts!B5:B532,B16,Parts!E5:E532,2) -> 5 | O16: =COUNTIFS(Parts!B5:B532,B16,Parts!E5:E532,3) -> 4 | P16: =COUNTIFS(Parts!B5:B532,B16,Parts!E5:E532,4) -> 4 | R16: 0.1025
B17: quilt-jev-toolkit | C17: organ | D17: /home/z/my-project/quilt-jev-toolkit | E17: c9840b2 | F17: PASS 44/44 (145ms) + boot-demo PASS + rewind-demo 7/7 stages PASS (all offline) | G17: Suite = 34 v0/v1 tests untouched + 10 v2 (signed checkpoints, partial custody). Demos re-ran fresh this lane and wrote their receipts (examples/receipts/boot-de | H17: Organ protocol v0→v2: verified custody bundles, rewind family, double-entry nesting, signed checkpoints. | I17: =COUNTIF(Parts!B5:B532,B17) -> 25 | J17: =COUNTIFS(Parts!B5:B532,B17,Parts!K5:K532,"<>") -> 25 | K17: =I17-J17 -> 0 | L17: =COUNTIFS(Parts!B5:B532,B17,Parts!E5:E532,0) -> 4 | M17: =COUNTIFS(Parts!B5:B532,B17,Parts!E5:E532,1) -> 7 | N17: =COUNTIFS(Parts!B5:B532,B17,Parts!E5:E532,2) -> 8 | O17: =COUNTIFS(Parts!B5:B532,B17,Parts!E5:E532,3) -> 3 | P17: =COUNTIFS(Parts!B5:B532,B17,Parts!E5:E532,4) -> 3 | R17: 0.086
B18: quilt-mcp-receipts | C18: organ | D18: /home/z/my-project/quilt-mcp-receipts | E18: 889960a | F18: PASS 15/15 (5.6s, offline) | G18: Every test spawns a real server process and speaks newline-delimited JSON-RPC over stdio; the test signer is re-derived from DESIGN.md §2, not imported from ser | H18: Fleet receipt chain as signed append-only MCP organ; fail-closed named errors. | I18: =COUNTIF(Parts!B5:B532,B18) -> 16 | J18: =COUNTIFS(Parts!B5:B532,B18,Parts!K5:K532,"<>") -> 16 | K18: =I18-J18 -> 0 | L18: =COUNTIFS(Parts!B5:B532,B18,Parts!E5:E532,0) -> 4 | M18: =COUNTIFS(Parts!B5:B532,B18,Parts!E5:E532,1) -> 4 | N18: =COUNTIFS(Parts!B5:B532,B18,Parts!E5:E532,2) -> 3 | O18: =COUNTIFS(Parts!B5:B532,B18,Parts!E5:E532,3) -> 3 | P18: =COUNTIFS(Parts!B5:B532,B18,Parts!E5:E532,4) -> 2 | R18: 0.0949
B19: quilt-research-canons | C19: organ | D19: /home/z/my-project/quilt-research-canons | E19: 3547d01 | F19: PASS — 5/5 sprint scripts fully conform to the SPRINT-LINEAGE contract; 3/3 JSON artifacts parse | G19: The sprint scripts themselves were NOT executed: they require API keys (env TYPESAFEAI_KEY etc.) and network calls to api.typesafe.ai / api.deepinfra.com (sprin | H19: Research canon documents: sprint-lineage protocol, pre-registered predictions, witnesses declaring successors. | I19: =COUNTIF(Parts!B5:B532,B19) -> 14 | J19: =COUNTIFS(Parts!B5:B532,B19,Parts!K5:K532,"<>") -> 9 | K19: =I19-J19 -> 5 | L19: =COUNTIFS(Parts!B5:B532,B19,Parts!E5:E532,0) -> 2 | M19: =COUNTIFS(Parts!B5:B532,B19,Parts!E5:E532,1) -> 3 | N19: =COUNTIFS(Parts!B5:B532,B19,Parts!E5:E532,2) -> 4 | O19: =COUNTIFS(Parts!B5:B532,B19,Parts!E5:E532,3) -> 2 | P19: =COUNTIFS(Parts!B5:B532,B19,Parts!E5:E532,4) -> 3 | R19: 0.1031
B20: quilt-quant | C20: labs | D20: /home/z/my-project/download/quilt-quant | E20: c20c1c8 | F20: PASS (17/17 checks green, 220ms, offline mode) | G20: Offline skips the 2 live-channel checks (19 live). Two local fixes were needed, no network used: (1) missing 'yaml' dep satisfied by symlink download/node_modul | H20: Trading desk as closed-loop cell sheet: simulate first, gated learning, receipts. | I20: =COUNTIF(Parts!B5:B532,B20) -> 14 | J20: =COUNTIFS(Parts!B5:B532,B20,Parts!K5:K532,"<>") -> 13 | K20: =I20-J20 -> 1 | L20: =COUNTIFS(Parts!B5:B532,B20,Parts!E5:E532,0) -> 2 | M20: =COUNTIFS(Parts!B5:B532,B20,Parts!E5:E532,1) -> 4 | N20: =COUNTIFS(Parts!B5:B532,B20,Parts!E5:E532,2) -> 4 | O20: =COUNTIFS(Parts!B5:B532,B20,Parts!E5:E532,3) -> 2 | P20: =COUNTIFS(Parts!B5:B532,B20,Parts!E5:E532,4) -> 2 | R20: 0.717
B21: quilt-dba | C21: labs | D21: /home/z/my-project/download/quilt-dba | E21: 7113eed | F21: PASS (13/13 checks) | G21: Honest negative: the repo-root `node smoke.mjs` FAILS (dba/driver.mjs:20 imports TASKS from dba/sheet.mjs which no longer exports it — SyntaxError). The canonic | H21: Developmental agent as 12-cell seed sheet: growth, conservation law, honest gates. | I21: =COUNTIF(Parts!B5:B532,B21) -> 15 | J21: =COUNTIFS(Parts!B5:B532,B21,Parts!K5:K532,"<>") -> 15 | K21: =I21-J21 -> 0 | L21: =COUNTIFS(Parts!B5:B532,B21,Parts!E5:E532,0) -> 3 | M21: =COUNTIFS(Parts!B5:B532,B21,Parts!E5:E532,1) -> 5 | N21: =COUNTIFS(Parts!B5:B532,B21,Parts!E5:E532,2) -> 3 | O21: =COUNTIFS(Parts!B5:B532,B21,Parts!E5:E532,3) -> 2 | P21: =COUNTIFS(Parts!B5:B532,B21,Parts!E5:E532,4) -> 2 | R21: 0.7387
B22: quilt-raw | C22: labs | D22: /home/z/my-project/download/quilt-raw | E22: e759163 | F22: PASS (18/18 checks sealed) | G22: Covers q32 arithmetic vs reference (i128>>32 wrap mul, truncating div, exact isqrt), tick 7-ops + ledger, transactional breach halt with ledger bit-unchanged, 5 | H22: v -> L -> G -> v' in exact integer arithmetic: seven ops, exact rewind, no search. | I22: =COUNTIF(Parts!B5:B532,B22) -> 14 | J22: =COUNTIFS(Parts!B5:B532,B22,Parts!K5:K532,"<>") -> 12 | K22: =I22-J22 -> 2 | L22: =COUNTIFS(Parts!B5:B532,B22,Parts!E5:E532,0) -> 2 | M22: =COUNTIFS(Parts!B5:B532,B22,Parts!E5:E532,1) -> 8 | N22: =COUNTIFS(Parts!B5:B532,B22,Parts!E5:E532,2) -> 0 | O22: =COUNTIFS(Parts!B5:B532,B22,Parts!E5:E532,3) -> 1 | P22: =COUNTIFS(Parts!B5:B532,B22,Parts!E5:E532,4) -> 3 | R22: 0.661
B23: cot-quilt | C23: labs | D23: /home/z/my-project/cot-quilt | E23: 0f360b9 | F23: PASS (offline ritual: verdict CLEAN, exit 0) + live pipeline NOT_RUN | G23: Live run needs DEEPSEEK/TYPESAFE/DEEPINFRA keys and network — forbidden by dog-food rules, so NOT_RUN with that reason. The offline credential scanner is green: | H23: Cheap models decompose a big model's CoT into a receipted cellular graph. | I23: =COUNTIF(Parts!B5:B532,B23) -> 12 | J23: =COUNTIFS(Parts!B5:B532,B23,Parts!K5:K532,"<>") -> 9 | K23: =I23-J23 -> 3 | L23: =COUNTIFS(Parts!B5:B532,B23,Parts!E5:E532,0) -> 1 | M23: =COUNTIFS(Parts!B5:B532,B23,Parts!E5:E532,1) -> 4 | N23: =COUNTIFS(Parts!B5:B532,B23,Parts!E5:E532,2) -> 3 | O23: =COUNTIFS(Parts!B5:B532,B23,Parts!E5:E532,3) -> 2 | P23: =COUNTIFS(Parts!B5:B532,B23,Parts!E5:E532,4) -> 2 | R23: 0.8006
B24: MicroMoth-quilt | C24: labs | D24: /home/z/my-project/MicroMoth-quilt | E24: b23055c | F24: PARTIAL (19 passed, 1 failed) | G24: Honest negative, and the failure is the design working: test_manifest_exists_and_matches FAILED because the tracked tree drifted AFTER the import-baseline manif | H24: Smallest quantum framework taught to keep receipts: circuit = hash-chained cell ledger. | I24: =COUNTIF(Parts!B5:B532,B24) -> 13 | J24: =COUNTIFS(Parts!B5:B532,B24,Parts!K5:K532,"<>") -> 10 | K24: =I24-J24 -> 3 | L24: =COUNTIFS(Parts!B5:B532,B24,Parts!E5:E532,0) -> 2 | M24: =COUNTIFS(Parts!B5:B532,B24,Parts!E5:E532,1) -> 5 | N24: =COUNTIFS(Parts!B5:B532,B24,Parts!E5:E532,2) -> 2 | O24: =COUNTIFS(Parts!B5:B532,B24,Parts!E5:E532,3) -> 2 | P24: =COUNTIFS(Parts!B5:B532,B24,Parts!E5:E532,4) -> 2 | R24: 0.766
B25: moth-research | C25: labs | D25: /home/z/my-project/moth-research | E25: c20c1c8 | F25: NOT_RUN (no executable entry point — docs-only research mooring) | G25: The repo is offline HTML snapshots of the Moth Quantum API docs (intro, endpoints, 7 engine pages), the vendored MicroMoth source, and the vendored quantum-audi | H25: Vendored quantum API docs + offline twins: the sourcing discipline behind lab entropy. | I25: =COUNTIF(Parts!B5:B532,B25) -> 10 | J25: =COUNTIFS(Parts!B5:B532,B25,Parts!K5:K532,"<>") -> 6 | K25: =I25-J25 -> 4 | L25: =COUNTIFS(Parts!B5:B532,B25,Parts!E5:E532,0) -> 2 | M25: =COUNTIFS(Parts!B5:B532,B25,Parts!E5:E532,1) -> 3 | N25: =COUNTIFS(Parts!B5:B532,B25,Parts!E5:E532,2) -> 2 | O25: =COUNTIFS(Parts!B5:B532,B25,Parts!E5:E532,3) -> 2 | P25: =COUNTIFS(Parts!B5:B532,B25,Parts!E5:E532,4) -> 1 | R25: 0.7344
B26: superinstance-site | C26: meta | D26: /home/z/my-project/download/superinstance | E26: c20c1c8 | F26: PASS | G26: 4 embedded script blocks extracted (4832/12981/21103/1988 bytes); largest parses clean under node --check. Full page NOT_RUN in DOM (needs headless Chromium; th | H26: the account's public face: brand, positioning map, QA manifesto — running cells instead of screenshots | I26: =COUNTIF(Parts!B5:B532,B26) -> 19 | J26: =COUNTIFS(Parts!B5:B532,B26,Parts!K5:K532,"<>") -> 10 | K26: =I26-J26 -> 9 | L26: =COUNTIFS(Parts!B5:B532,B26,Parts!E5:E532,0) -> 2 | M26: =COUNTIFS(Parts!B5:B532,B26,Parts!E5:E532,1) -> 5 | N26: =COUNTIFS(Parts!B5:B532,B26,Parts!E5:E532,2) -> 5 | O26: =COUNTIFS(Parts!B5:B532,B26,Parts!E5:E532,3) -> 3 | P26: =COUNTIFS(Parts!B5:B532,B26,Parts!E5:E532,4) -> 4 | R26: 0.067
B27: quilt-upstream | C27: meta | D27: /home/z/my-project/quilt-upstream-main | E27: fdfed69 | F27: PASS | G27: Upstream engine core: 4 test files, 36/36 passed in 954ms, fully offline (vitest resolved from the repo's own node_modules). Also python3 -m py_compile quilt-ke | H27: the upstream quilt repo (external origin, Lucineer): the engine core the fleet knows, plus an out-of-superinstance idea corpus of essays and papers | I27: =COUNTIF(Parts!B5:B532,B27) -> 24 | J27: =COUNTIFS(Parts!B5:B532,B27,Parts!K5:K532,"<>") -> 9 | K27: =I27-J27 -> 15 | L27: =COUNTIFS(Parts!B5:B532,B27,Parts!E5:E532,0) -> 2 | M27: =COUNTIFS(Parts!B5:B532,B27,Parts!E5:E532,1) -> 11 | N27: =COUNTIFS(Parts!B5:B532,B27,Parts!E5:E532,2) -> 7 | O27: =COUNTIFS(Parts!B5:B532,B27,Parts!E5:E532,3) -> 0 | P27: =COUNTIFS(Parts!B5:B532,B27,Parts!E5:E532,4) -> 4 | R27: 0.1609
B28: breakthrough-prospector | C28: meta | D28: /home/z/my-project/breakthrough-prospector | E28: f0034fd | F28: PASS | G28: The scorer RAN offline and emitted the live table: E1 80 RUN (bug-injection self-play), E6 64 RUN, E3 60 RUN with '! F cap: external dependency (Casey)', E7 60 | H28: a pipeline that turns frontier scouting into pre-registered, receipt-backed experiments — crossing abstractions systematically instead of by luck at 3am | I28: =COUNTIF(Parts!B5:B532,B28) -> 16 | J28: =COUNTIFS(Parts!B5:B532,B28,Parts!K5:K532,"<>") -> 9 | K28: =I28-J28 -> 7 | L28: =COUNTIFS(Parts!B5:B532,B28,Parts!E5:E532,0) -> 2 | M28: =COUNTIFS(Parts!B5:B532,B28,Parts!E5:E532,1) -> 5 | N28: =COUNTIFS(Parts!B5:B532,B28,Parts!E5:E532,2) -> 5 | O28: =COUNTIFS(Parts!B5:B532,B28,Parts!E5:E532,3) -> 2 | P28: =COUNTIFS(Parts!B5:B532,B28,Parts!E5:E532,4) -> 2 | R28: 0.5179
B29: craftmind-study | C29: meta | D29: /home/z/my-project/craftmind-study | E29: c20c1c8 | F29: PASS | G29: Core ranch modules parse clean. Test suites NOT_RUN: tests/test-all.js + integration tests target a Worker/runtime harness not present offline; live instances a | H29: study of three sibling Cocapn-fleet experiments where learning is emergent and verified-work-only: evolving ranch bots, a blank-slate researcher, correction-trained sheepdogs | I29: =COUNTIF(Parts!B5:B532,B29) -> 16 | J29: =COUNTIFS(Parts!B5:B532,B29,Parts!K5:K532,"<>") -> 5 | K29: =I29-J29 -> 11 | L29: =COUNTIFS(Parts!B5:B532,B29,Parts!E5:E532,0) -> 3 | M29: =COUNTIFS(Parts!B5:B532,B29,Parts!E5:E532,1) -> 5 | N29: =COUNTIFS(Parts!B5:B532,B29,Parts!E5:E532,2) -> 6 | O29: =COUNTIFS(Parts!B5:B532,B29,Parts!E5:E532,3) -> 1 | P29: =COUNTIFS(Parts!B5:B532,B29,Parts!E5:E532,4) -> 1 | R29: 0.4297
B30: quilt-atlas | C30: meta | D30: /home/z/my-project/quilt-atlas | E30: 5aa850d | F30: PASS | G30: Generator parses clean. Full re-inventory NOT_RUN: requires GITHUB_TOKEN and network (per README usage), both out of scope for this lane. atlas.json itself was | H30: prior atlas: a 6h scheduled re-inventory of the account with auditable classification and honest UNMEASURED vocabulary — superseded by wave-66, which decomposes ideas, not repo surfaces | I30: =COUNTIF(Parts!B5:B532,B30) -> 12 | J30: =COUNTIFS(Parts!B5:B532,B30,Parts!K5:K532,"<>") -> 6 | K30: =I30-J30 -> 6 | L30: =COUNTIFS(Parts!B5:B532,B30,Parts!E5:E532,0) -> 2 | M30: =COUNTIFS(Parts!B5:B532,B30,Parts!E5:E532,1) -> 2 | N30: =COUNTIFS(Parts!B5:B532,B30,Parts!E5:E532,2) -> 3 | O30: =COUNTIFS(Parts!B5:B532,B30,Parts!E5:E532,3) -> 1 | P30: =COUNTIFS(Parts!B5:B532,B30,Parts!E5:E532,4) -> 4 | R30: 0.315
B31: quilt-codespace | C31: meta | D31: /home/z/my-project/quilt-codespace | E31: c8355d6 | F31: PASS | G31: The HTTP API server parses clean. Booting the three-service stack NOT_RUN: it is a Codespace deployment (ttyd + HTTP + dashboard via post-create.sh) and the scr | H31: codespace lane: quilt as a live token-authenticated federated runtime in a browser-terminal Codespace, subscribing to ESP32/Jetson/Cloud siblings | I31: =COUNTIF(Parts!B5:B532,B31) -> 14 | J31: =COUNTIFS(Parts!B5:B532,B31,Parts!K5:K532,"<>") -> 3 | K31: =I31-J31 -> 11 | L31: =COUNTIFS(Parts!B5:B532,B31,Parts!E5:E532,0) -> 2 | M31: =COUNTIFS(Parts!B5:B532,B31,Parts!E5:E532,1) -> 4 | N31: =COUNTIFS(Parts!B5:B532,B31,Parts!E5:E532,2) -> 3 | O31: =COUNTIFS(Parts!B5:B532,B31,Parts!E5:E532,3) -> 4 | P31: =COUNTIFS(Parts!B5:B532,B31,Parts!E5:E532,4) -> 1 | R31: 0.2474
B32: si-fleet | C32: meta | D32: /home/z/my-project/si-fleet | E32: c20c1c8 | F32: PASS | G32: tidepool suite runs fully offline on mocks: 'tide-pool smoke: 18 passed, 0 failed' + node:test 13/13 pass (98ms) covering JEV gate floor refusal, sigma agreemen | H32: fleet infrastructure as one monorepo of lanes: a shared context ocean, edge quilt runtimes, AI cells, canon headers | I32: =COUNTIF(Parts!B5:B532,B32) -> 16 | J32: =COUNTIFS(Parts!B5:B532,B32,Parts!K5:K532,"<>") -> 8 | K32: =I32-J32 -> 8 | L32: =COUNTIFS(Parts!B5:B532,B32,Parts!E5:E532,0) -> 2 | M32: =COUNTIFS(Parts!B5:B532,B32,Parts!E5:E532,1) -> 4 | N32: =COUNTIFS(Parts!B5:B532,B32,Parts!E5:E532,2) -> 5 | O32: =COUNTIFS(Parts!B5:B532,B32,Parts!E5:E532,3) -> 3 | P32: =COUNTIFS(Parts!B5:B532,B32,Parts!E5:E532,4) -> 2 | R32: 0.0698
B33: external-scouts | C33: meta | D33: /home/z/my-project/jev-garden/scouts/raw | E33: d05e1d9 | F33: PASS | G33: All 5 raw scout JSONs parse: V-JEPA_2_JEPA_world_mode.json (4 results), test-time_training_layer.json (7), knowledge_distillation_L.json (7), hyperdimensional_c | H33: out-of-superinstance research moorings: five raw web-search receipts the garden synthesized into design justifications — one channel returned junk and was receipted, not hidden | I33: =COUNTIF(Parts!B5:B532,B33) -> 17 | J33: =COUNTIFS(Parts!B5:B532,B33,Parts!K5:K532,"<>") -> 5 | K33: =I33-J33 -> 12 | L33: =COUNTIFS(Parts!B5:B532,B33,Parts!E5:E532,0) -> 1 | M33: =COUNTIFS(Parts!B5:B532,B33,Parts!E5:E532,1) -> 4 | N33: =COUNTIFS(Parts!B5:B532,B33,Parts!E5:E532,2) -> 9 | O33: =COUNTIFS(Parts!B5:B532,B33,Parts!E5:E532,3) -> 1 | P33: =COUNTIFS(Parts!B5:B532,B33,Parts!E5:E532,4) -> 2 | R33: 0.3726

Sheet Parts
B2: Elementary parts (528 rows — spreadsheet logic)
B4: work | C4: family | D4: part_id | E4: layer | F4: layer_name | G4: name | H4: essence | I4: inputs | J4: outputs | K4: gate | L4: gate_kind | M4: failure_mode | N4: elementary | O4: evidence
B5: qthe | C5: substrate | D5: qthe-P01 | E5: 0 | F5: substrate | G5: pack/unpack bijection over one byte | H5: c <-> (tau, d) is an exact bijection onto {0..3} x {0..63}; bit 7-6 tau, bit 5-0 d. | I5: tau, d | J5: packed byte c, unpacked {tau,d} | K5: 256/256 values round-trip exact AND 256 distinct packed outputs (gate G1) | L5: postcondition | M5: any overlap or lossy round-trip would break every downstream trace hash | N5: yes | O5: qthe.mjs:66-69
B6: qthe | C6: substrate | D6: qthe-P02 | E6: 0 | F6: substrate | G6: Psi operator map | H6: The timbre-to-operator character table {0:0, 1:+1, 2:-1, 3:'i'} — Ground contributes to nothing, Attract amplifies, Repel inverts, Abstain is the looking-glass. | I6: tau | J6: operator character 0 | +1 | -1 | 'i' | K6: PSI === [0, 1, -1, 'i'] asserted by G1 | L6: invariant | N6: yes | O6: qthe.mjs:58-63
B7: qthe | C7: substrate | D7: qthe-P03 | E7: 0 | F7: substrate | G7: split-channel vector pass (integer-exact) | H7: y_j^R = sum(Attract d*x) - sum(Repel d*x), y_j^I = sum(Abstain d*x); Ground excluded even with d>0; no floats in LAYER 0. | I7: weights rows of packed bytes, integer xs | J7: {re, im} per output channel j | K7: hand-computed fixtures exact and every output Number.isInteger (G4: row0 [A10,R4,I6,G63] x xs[2,3,5,7] -> {re:8, im:30}) | L7: postcondition | M7: float leakage or a wrong channel assignment would fail the literal fixtures | N7: yes | O7: qthe.mjs:77-95
B8: qthe | C8: substrate | D8: qthe-P04 | E8: 0 | F8: substrate | G8: substrate allocation with named expandos | H8: makeSubstrate returns a Uint8Array carrying w, h, ticks, __wormholes and bytes as named properties; serialize via traceView, never JSON.stringify. | I8: w, h, seedFn(x,y,i) | J8: row-major packed cell plane | K8: w, h positive integers else RangeError | L8: precondition | M8: JSON.stringify would leak expandos into traces (receipted as R5) | N8: yes | O8: qthe.mjs:148-160
B9: qthe | C9: substrate | D9: qthe-P05 | E9: 1 | F9: mechanism | G9: 64-slot wormhole table | H9: Static allocation, zero runtime discovery: slot s is empty or {x, y, resonance}; sigma parameter default log2(3). | I9: sigma | J9: read(slot), write(slot,x,y,resonance), snapshot() | K9: exactly SLOT_COUNT=64 slots; write outside [0,64) throws RangeError | L9: invariant | N9: yes | O9: qthe.mjs:99-142
B10: qthe | C10: substrate | D10: qthe-P06 | E10: 1 | F10: mechanism | G10: twin-resonance read guard | H10: An Abstain cell with data d reads slot d live; a hit counts only if the occupant is a different (x,y) with resonance != 0; the term resonance*sigma is added to pressure and emitted as an event. | I10: slot=d of the Abstain cell, wormhole table | J10: pressure adjustment, twin event {kind,x,y,slot,resonance,term} | K10: lone Abstain cell never twins after its own first write; every event term === log2(3) exactly (G5 schedule) | L10: postcondition | M10: self-resonance (same x,y) or resonance=0 would make single cells self-excite | N10: yes | O10: qthe.mjs:217-224
B11: qthe | C11: substrate | D11: qthe-P07 | E11: 1 | F11: mechanism | G11: wormhole write, last-writer-wins | H11: After pressure, an Abstain cell writes its own (x, y) and resonance = |real_acc| + 1 to slot d; collisions resolve last-writer-wins while live reads keep same-slot twins mutually audible. | I11: x, y, |acc|+1, slot=d | J11: occupied slot, totalWrites++ | K11: totalWrites = 12 after the G5 6-tick twin fixture | L11: postcondition | N11: yes | O11: qthe.mjs:123-128, 224
B12: qthe | C12: substrate | D12: qthe-P08 | E12: 2 | F12: policy | G12: sigma bridge scale policy | H12: sigma defaults to log2(3) but is a swept parameter: with sigma~1.585 a lone twin flips exactly one unit of net-negative pressure, so the C3 sweep is a real dynamics sweep, not decoration. | I12: sigma override | J12: imaginary pressure scale | K12: the SPEC prices sigma as OPEN: only the sweep {log2(3), 0.5, 1, 2, 4} decides (C3); the gifted 'proof' is receipted as decorative | L12: budget | M12: treating log2(3) as proven would be LARP; SPEC.md receipted it as decorative | N12: yes | O12: qthe.mjs:100, 28-35; SPEC.md:75
B13: qthe | C13: substrate | D13: qthe-P09 | E13: 1 | F13: mechanism | G13: pre-tick snapshot double buffer | H13: Neighbors are always read from the pre-tick grid so in-place update stays synchronous-exact (interpretation receipt R2/R6). | I13: current cells | J13: snap copy reused via __scratch | K13: tick mutates in place and returns the same substrate with synchronous-exact semantics | L13: invariant | N13: yes | O13: qthe.mjs:172-194
B14: qthe | C14: substrate | D14: qthe-P10 | E14: 1 | F14: mechanism | G14: Moore-8 branchless real accumulator | H14: Eight toroidal neighbor reads in fixed order: Attract adds d, Repel subtracts d into the real accumulator; fixed order is what makes the wormhole live-read deterministic. | I14: snap, x, y | J14: integer acc in [-504, 504] | K14: G2 full-tick exhaustion: 3840/3840 cell-updates in bounds with tau preserved | L14: invariant | N14: yes | O14: qthe.mjs:197-214
B15: qthe | C15: substrate | D15: qthe-P11 | E15: 1 | F15: mechanism | G15: nextD saturation rule | H15: Pure rule table: net-positive pressure moves d toward min(d+1, 63), net-negative toward 0, zero leaves d unchanged. | I15: d, pressure | J15: new d in [0,63] | K15: 2304/2304 exhausted states x 9 pressures stay in [0,63] (G2a — the Coq theorem restated by exhaustion) | L15: postcondition | N15: yes | O15: qthe.mjs:166-170
B16: qthe | C16: substrate | D16: qthe-P12 | E16: 1 | F16: mechanism | G16: timbre frozen inside tick | H16: tau never changes inside tick — timbre is written only by injectors — which keeps the C2 paired arms clean and the byte's only dynamics in d. | I16: cell byte | J16: cell byte with identical tau | K16: G2: tau preserved EXACTLY on 3840/3840 updates | L16: invariant | M16: any tau mutation inside tick would contaminate the paired-arm C2 comparison | N16: yes | O16: qthe.mjs:163-165, 226
B17: qthe | C17: substrate | D17: qthe-P13 | E17: 1 | F17: mechanism | G17: toroidal Moore-8 edges (R1) | H17: Edges wrap, so every cell has exactly 8 neighbors and the update rule is one uniform table with no boundary special case. | I17: w, h | J17: wrap indices (y+h-1)%h, (x+1)%w, ... | N17: yes | O17: qthe.mjs:18-19, 198-205
B18: qthe | C18: substrate | D18: qthe-P14 | E18: 1 | F18: mechanism | G18: determinism contract: no Math.random in the kernel | H18: mulberry32 exists only as a SEEDED caller-side generator; tick never draws randomness; same substrate + same opts is byte-identical. | I18: substrate, opts | J18: deterministic advanced substrate | K18: G3: two substrates, 1000 ticks, all per-tick trace hashes byte-identical; different seed differs; static scan finds ZERO Math.random in the kernel | L18: seal | M18: a nondeterministic tick would void every experiment (determinism or it didn't happen) | N18: yes | O18: qthe.mjs:10-13, 253-265
B19: qthe | C19: substrate | D19: qthe-P15 | E19: 3 | F19: interface | G19: traceView canonical serialization | H19: The single JSON-able view of substrate + table + tick events that G3/G6 hash and the A2UI HUD displays; expandos never enter the view and wormhole STATE is recorded, not the flag (R7). | I19: cells, events | J19: {w,h,ticks,cells,wormholes,events} | K19: an empty table is trace-equivalent to wormholes disabled; paired arms byte-equal with zero Abstain cells (G6/S2) | L19: invariant | M19: R7: on the first G6 run the flag itself leaked into traces — found by the gate and receipted | N19: yes | O19: qthe.mjs:243-251
B20: qthe | C20: substrate | D20: qthe-P16 | E20: 2 | F20: policy | G20: paired-arm wormholes flag | H20: opts.wormholes=false disables table reads AND writes (the OFF arm); without Abstain cells the flag must not leak into dynamics at all. | I20: opts.wormholes, substrate | J20: ON/OFF arm pair for C2 | K20: G6/S1: ON-trace != OFF-trace (divergence tick exists); G6/S2: with zero Abstain cells ON === OFF byte-identical at all 200 ticks | L20: postcondition | N20: yes | O20: qthe.mjs:175-190; SPEC.md:74
B21: qthe | C21: substrate | D21: qthe-P17 | E21: 4 | F21: evidence | G21: pre-registered gate predictions G0-G6 | H21: Each gate's prediction is written into the test header BEFORE the first run, per house law; the run records observed numbers; exit 0 iff all gates PASS. | I21: qthe.mjs kernel | J21: tests/receipt.json verdicts + observed | K21: honest FAILs stay in the receipt chain, never rewritten | L21: seal | N21: yes | O21: tests/run_tests.mjs:1-9, 79-80
B22: qthe | C22: substrate | D22: qthe-P18 | E22: 4 | F22: evidence | G22: stone-v1 receipt chain for tests | H22: A receipt without a chain is a rumor: G1-G6 seal into tests/receipts.jsonl with observed numbers, fully deterministic so a re-run rewrites identical bytes. | I22: gate results | J22: receipt.json + receipts.jsonl stone chain | K22: re-run produces byte-identical receipts | L22: seal | N22: yes | O22: qthe.mjs:53-54; tests/run_tests.mjs:78-80
B23: qthe | C23: substrate | D23: qthe-P19 | E23: 4 | F23: evidence | G23: honest-FAIL preservation (G4 erratum) | H23: G4's pre-registered re-literal contained a hand-arithmetic error; the gate FAILS BY LETTER forever and the corrected literal is checked by a post-hoc gate G4-P2 — prediction was wrong, not the kernel; registered gates are never rewritten. | I23: registered G4 literal | J23: standing FAIL + erratum + correction gate | K23: the registered literal is never edited post-registration | L23: invariant | M23: rewriting the registered gate would be tampering with the pre-registration discipline | N23: yes | O23: tests/run_tests.mjs:38-46
B24: qthe | C24: substrate | D24: qthe-P20 | E24: 4 | F24: evidence | G24: two-reader negative controls | H24: An independent stdlib-only reader walks registered receipt chains and must fail closed: one flipped byte in every row localizes to exactly that row (49/49), plus missing-file, wrong-tip, unknown-chain and mutated-pin-table refusals. | I24: registered chains, pin table with seal | J24: self-test receipt {cases_total:54, escapes:0} | K24: exit 0 iff every negative control was DETECTED and localized to the correct row | L24: postcondition | M24: any escape (tamper passing silently) is the named catastrophe this part exists to refuse | N24: yes | O24: two_reader/selftest.mjs:6-22; two_reader/verdict.md:1-10
B25: qthe | C25: substrate | D25: qthe-P21 | E25: 2 | F25: policy | G25: priced empirical claims C1-C5 | H25: Layer-2 claims from the gifted corpus (gain of function, wormhole vs traversal, sigma criticality, phase threshold, self-repair) are pre-registered as paired arms with floors — all OPEN, honest null is a crown jewel. | I25: paired-arm experiment designs | J25: claim status table | K25: a claim that dies dies cheap and honest with the receipt kept beside the body; a claim that lives owes a mechanism-level explanation | L25: admission | M25: C3's gifted 'proof' is receipted as decorative (the Gaussian integral yields sigma*sqrt(2pi) for ANY sigma) — only the sweep decides | N25: yes | O25: SPEC.md:69-81
B26: qthe | C26: substrate | D26: qthe-P22 | E26: 3 | F26: interface | G26: A2UI telemetry mapping | H26: The live mirror: pixel = cell, tau=1 green, tau=2 red, tau=0 gray, tau=3 purple blinking on wormhole activity, 6-bit value = intensity, direct buffer-to-canvas, no log files. | I26: substrate bytes | J26: canvas pixels | K26: HUD SHA stable across reload (demo/smoke screenshots receipted) | L26: postcondition | N26: yes | O26: SPEC.md:65-67; demo/smoke/smoke.md:17 (checklist item c: HUD sha stable across reloads, cross-runtime MATCH)
B27: quilt-jepa | C27: substrate | D27: quilt-jepa-P01 | E27: 0 | F27: substrate | G27: xorshift32 deterministic seed | H27: The only randomness source: a 32-bit xorshift generator; seed 0 is coerced to the golden-ratio constant so seed space is total. | I27: u32 seed | J27: deterministic [0,1) stream | K27: no Math.random anywhere in core (determinism claim P4 PASS) | L27: invariant | M27: any hidden nondeterminism voids every byte-exact cross-round binding | N27: yes | O27: core/world.js:6-15
B28: quilt-jepa | C28: substrate | D28: quilt-jepa-P02 | E28: 0 | F28: substrate | G28: wave + ball observation field | H28: A 16x16 luminance field from two phased sinusoids plus a 2x2 ball bump clipped to 1 — the entire observable universe of the world model. | I28: world state (phases, freq, ball) | J28: Float32Array 256 luminances in [0,1] | K28: values are projections in [0,1] (v*0.5+0.5, min(1, ...)) | L28: invariant | N28: yes | O28: core/world.js:39-56
B29: quilt-jepa | C29: substrate | D29: quilt-jepa-P03 | E29: 0 | F29: substrate | G29: per-cell 4-dim features | H29: The local observable: [luminance, right-diff, down-diff, luminance-0.5] — the features each cell's encoder reads. | I29: obs, cell index i | J29: 4-vector f | N29: yes | O29: core/jepa.js:16-23
B30: quilt-jepa | C30: substrate | D30: quilt-jepa-P04 | E30: 1 | F30: mechanism | G30: per-cell context encoder Wc | H30: One 4x4 matrix per cell (Float32Array CELLS*16), xorshift-seeded at scale 0.5; encode maps features to the cell's latent. | I30: obs features per cell | J30: context latents z (CELLS x 4) | N30: yes | O30: core/jepa.js:34-47, 48-56
B31: quilt-jepa | C31: substrate | D31: quilt-jepa-P05 | E31: 1 | F31: mechanism | G31: per-cell predictor Wp | H31: One 4x4 matrix per cell predicting the next latent from the current context latent — the JEPA's learned dynamics. | I31: z_ctx | J31: z_pred | N31: yes | O31: core/jepa.js:66-73
B32: quilt-jepa | C32: substrate | D32: quilt-jepa-P06 | E32: 1 | F32: mechanism | G32: EMA target encoder Wt (stop-gradient) | H32: Wt = tau*Wt + (1-tau)*Wc with tau=0.999 (later pace-aware), providing the stable target the encoder chases — the law that prevents representation collapse. | I32: Wc, tau | J32: Wt target latents | K32: stationarity drift < 0.01 (claim R2v4 PASS, drift 2.640e-3) | L32: postcondition | M32: an unstable target would let the encoder chase itself into collapse | N32: yes | O32: core/jepa.js:39-46, 110-113
B33: quilt-jepa | C33: substrate | D33: quilt-jepa-P07 | E33: 1 | F33: mechanism | G33: clipped-SGD trainStep | H33: One hand-derived step: gradient 2*(zPred - zTgt)/N clipped to [-1,1], backprop through Wp then Wc, returns the loss — plain readable autodiff by hand. | I33: obs_t, obs_t+1 | J33: updated Wc, Wp, scalar loss L | K33: learning-sanity ratio 0.34923 == run4 pin, re-bound bit-exact through round 10 | L33: postcondition | M33: P1_learning honestly FAILED on the easy world (ratio 0.948) in run 1 — kept as the verdict | N33: yes | O33: core/jepa.js:80-115
B34: quilt-jepa | C34: substrate | D34: quilt-jepa-P08 | E34: 1 | F34: mechanism | G34: deterministic corruption probe | H34: corruptWc flips the sign of a seeded fraction of Wc weights — the fault-injection lever for the zero-self-repair and cure-arm experiments. | I34: fraction, seed | J34: corrupted Wc, count flipped | K34: P6_zero_self_repair honestly FAILed in run 1 (jump_ratio 0.979) — the fault was permanent, receipted as design law paid for | L34: postcondition | N34: yes | O34: core/jepa.js:123-130; receipts/run.json verdicts
B35: quilt-jepa | C35: substrate | D35: quilt-jepa-P09 | E35: 0 | F35: substrate | G35: stride-4 mesh cells | H35: The mesh substrate: per-cell Float32 stride 4 [luminance, angle, gradient magnitude, latent/surprise energy], double-buffered with an active-side flag. | I35: obs, energy | J35: two n*4 buffers | K35: lambda = 0.2 <= 0.25 stability bound | L35: invariant | M35: lambda above 0.25 would make diffusion diverge | N35: yes | O35: core/mesh.js:1-17
B36: quilt-jepa | C36: substrate | D36: quilt-jepa-P10 | E36: 1 | F36: mechanism | G36: Perona-Malik diffusion step | H36: One pass on channel 3: each cell exchanges energy with 4 neighbors scaled by conductance exp(-((mc-nb)^2)/kappaSq) — flow pools in flat regions and stalls at edges. | I36: src buffer | J36: dst buffer (buffers swapped) | K36: total energy conserved to 1.2e-8 relative (P5 PASS; my scratch rerun measured 0.0 over 10 steps) | L36: conservation | M36: any asymmetry in the pairwise exchange would mint or destroy energy | N36: yes | O36: core/mesh.js:33-55
B37: quilt-jepa | C37: substrate | D37: quilt-jepa-P11 | E37: 1 | F37: mechanism | G37: variance contraction readout | H37: totals() folds the active buffer into {total, mean, variance}; the registered law requires variance non-increasing under diffusion. | I37: active buffer | J37: {total, mean, variance} | K37: p5_variance_non_increasing true (receipts/run.json) | L37: postcondition | N37: yes | O37: core/mesh.js:56-64
B38: quilt-jepa | C38: substrate | D38: quilt-jepa-P12 | E38: 2 | F38: policy | G38: surprise sampling policy | H38: surprise(sampleIdx) is mean |energy| over chosen cells — upgraded across rounds to percentile-z concentration statistics rather than global means (design law (b): diluted mean-surprise was the root cause of run-1's anomaly FAIL). | I38: energy channel, sample indices | J38: scalar surprise / z-concentration | K38: R3v4 z-conc 3.5407 > 3.0 (PASS, carried) | L38: postcondition | M38: global mean-surprise diluted the anomaly signal — the honest FAIL that forced law (b) | N38: yes | O38: core/mesh.js:65-70; README.md:26-28
B39: quilt-jepa | C39: substrate | D39: quilt-jepa-P13 | E39: 4 | F39: evidence | G39: registration seal (masked self-sha + mtime) | H39: Claims are sealed into registration.json BEFORE runs: the file hashes itself with its own sha field masked; the verifier recomputes and also binds the file mtime within 2s. | I39: registration.json bytes, stat mtime | J39: seal verdict | K39: masked self-sha recomputes exactly AND |mtime - sealed| <= 2000ms else fail-closed | L39: seal | M39: file mutated after seal -> 'FAIL registration self-sha mismatch (file mutated after seal)' | N39: yes | O39: verify.mjs:32-43
B40: quilt-jepa | C40: substrate | D40: quilt-jepa-P14 | E40: 4 | F40: evidence | G40: stone chain walk from GENESIS | H40: Every receipt row hashes as sha(prev : canonical{i,id,type,payload} : id); the verifier re-derives the whole chain from the JEPA-GENESIS-1 constant and demands the tip match. | I40: receipts/run.json | J40: chain verdict + tip | K40: every row re-hashes to its pin, links parent-correct, tip equal; exit 0 only if everything re-hashes | L40: postcondition | M40: 'FAIL hash mismatch at row N' names the tampered row | N40: yes | O40: verify.mjs:12-30
B41: quilt-jepa | C41: substrate | D41: quilt-jepa-P15 | E41: 2 | F41: policy | G41: fail-closed startup seal re-verification | H41: The run itself re-verifies the registration seal at startup and refuses to execute otherwise; the verdict is recorded in the receipt (seal_verified_at_startup). | I41: registration-v10.json at run time | J41: refusal or execution | K41: seal verified at startup, else the run refuses | L41: admission | M41: running against a mutated registration would decouple claims from measurements | N41: yes | O41: run10.mjs:24-26; verdict-v10.md:3-5
B42: quilt-jepa | C42: substrate | D42: quilt-jepa-P16 | E42: 4 | F42: evidence | G42: bit-exact cross-round re-binding | H42: Every round 4..9 metric must reproduce its round's receipt bit-exactly at sha level (run4 29/29, run5 92/92, design6/run6..run9 identities); the R4 twin executions are byte-identical (sha_round10_run1 == run2). | I42: carried receipts, fresh execution | J42: re-bound shas in the R4 row | K42: any sha mismatch fails the run — the operating point (lr 0.3, tau 0.99998, K4, amp, seed) is UNCHANGED or the round is void | L42: postcondition | M42: a core arithmetic change would break ten rounds of pinned shas | N42: yes | O42: run10.mjs:2-19; verdict-v10.md:26-28
B43: quilt-jepa | C43: substrate | D43: quilt-jepa-P17 | E43: 4 | F43: evidence | G43: honest-FAIL verdicts carried forward | H43: DOSE10, SAT10, DIP10 are scored FAIL on pre-priced branches; the round-8 MECH FAIL and round-9 CURE9/DIP9 FAILs carry — 22/28 with the failures in the scorecard, not footnotes. | I43: claim scorecard rules | J43: verdict fields (28 keys, 22 true) | K43: claims_passed reported as measured, never rounded up | L43: postcondition | N43: yes | O43: verdict-v10.md:25-31
B44: quilt-jepa | C44: substrate | D44: quilt-jepa-P18 | E44: 3 | F44: interface | G44: browser demo labeled DESIGN-ONLY | H44: demo/index.html is a WebGPU/WGSL visualization of the same architecture, explicitly never executed headless and never cited as evidence — the interface/artifact boundary is receipted in the README. | I44: architecture design | J44: browser visualization | K44: DESIGN/DEMO ONLY — no headless execution claim | L44: admission | M44: citing the demo as a verified result would be LARP | N44: yes | O44: README.md:22
B45: jev-quilt | C45: substrate | D45: jev-quilt-P01 | E45: 0 | F45: substrate | G45: cell identity law | H45: coord must be a tuple of two integers (k, s); anything else raises TypeError at construction — identity never floats (Law 1). | I45: name, coord | J45: Cell (or TypeError) | K45: non-integer or non-pair coord is refused at __post_init__ | L45: admission | M45: a float coordinate would silently create an unfoundable identity | N45: yes | O45: jev_quilt/cell.py:37-54
B46: jev-quilt | C46: substrate | D46: jev-quilt-P02 | E46: 0 | F46: substrate | G46: Hook subscription primitive | H46: A frozen Hook names a source cell, fires on delta, carries a DEADBAND token or a Q16 magnitude floor, and an optional when-predicate on the emitted state (the touch-shallow gate). | I46: source, floor, when | J46: subscription object | N46: yes | O46: jev_quilt/cell.py:16-26
B47: jev-quilt | C47: substrate | D47: jev-quilt-P03 | E47: 3 | F47: interface | G47: Projection declaration | H47: Outputs are declared edges (to, as_type): json | coefficient | choice | bytes — this cell renders, another cell decides; types are declared at the edge (Law 3). | I47: decision | J47: typed payload on a named surface | N47: yes | O47: jev_quilt/cell.py:29-35
B48: jev-quilt | C48: substrate | D48: jev-quilt-P04 | E48: 2 | F48: policy | G48: binary viability floor | H48: A decision may LINK/project only above the floor: default viability is confidence > 0.0; pure difference without viability collapses into dada noise (Law 5). | I48: decision (with confidence) | J48: viable bool | K48: confidence is None -> viable; else confidence > 0.0 required | L48: admission | M48: below-floor decisions are booked as REJECTED, never projected | N48: yes | O48: jev_quilt/cell.py:56-62
B49: jev-quilt | C49: substrate | D49: jev-quilt-P05 | E49: 0 | F49: substrate | G49: Q16 exact rational | H49: Identity arithmetic on (num, den): always reduced coprime, negative denominators normalized, zero denominator raises — the same codec as the fleet's lattice kernel. | I49: num:int, den:int | J49: exact Q16 with exact +, -, * | K49: den == 0 raises ZeroDivisionError; gcd reduction is an invariant | L49: invariant | N49: yes | O49: jev_quilt/q16.py:14-45
B50: jev-quilt | C50: substrate | D50: jev-quilt-P06 | E50: 2 | F50: policy | G50: from_float projection refusal | H50: Projection INTO the lattice: a float becomes Q16 only if num/SCALE reproduces it within 1e-12; anything else is refused — never silently rounded identity. | I50: float f | J50: Q16(num, 10^6) or ValueError | K50: |num/SCALE - f| > 1e-12 -> ValueError | L50: admission | M50: silent rounding would corrupt every downstream exact decision | N50: yes | O50: jev_quilt/q16.py:22-28
B51: jev-quilt | C51: substrate | D51: jev-quilt-P07 | E51: 2 | F51: policy | G51: deadband floor check | H51: A hook wakes only if |delta| >= floor; the DEADBAND token or None floor means no filtering; magnitudes are exact Q16. | I51: hook.floor, delta | J51: passes_floor bool | K51: mag >= floor else silent_deadband | L51: precondition | N51: yes | O51: jev_quilt/engine.py:67-74
B52: jev-quilt | C52: substrate | D52: jev-quilt-P08 | E52: 2 | F52: policy | G52: unmeasurable deltas wake (honest default) | H52: A delta with no extractable Q16 magnitude always wakes the hook — fail-open for unmeasurable shapes, the opposite of silently dropping what you can't measure. | I52: delta | J52: None magnitude -> wake | K52: mag is None -> return True | L52: precondition | M52: the named risk is noise amplification, accepted and receipted as the honest default | N52: yes | O52: jev_quilt/engine.py:70-72
B53: jev-quilt | C53: substrate | D53: jev-quilt-P09 | E53: 1 | F53: mechanism | G53: emit fanout with logged silence | H53: emit(source, delta, state) walks every hooked subscriber: below-floor/declining hooks are logged as WakeResult(woke=False, reason='silent_deadband'), others wake — silence is a recorded outcome, never an absence. | I53: source delta, state | J53: list[WakeResult] | K53: every hooked cell gets exactly one WakeResult per emit | L53: conservation | N53: yes | O53: jev_quilt/engine.py:76-91
B54: jev-quilt | C54: substrate | D54: jev-quilt-P10 | E54: 2 | F54: policy | G54: broken predicate fail-open | H54: A when-predicate that raises must NOT silence the fabric: the exception is caught and the hook wakes — the failure direction is chosen explicitly. | I54: hook.when(state) | J54: bool (True on exception) | K54: exception -> wake (never drop) | L54: invariant | M54: an exception inside a predicate silently starving cells is the named catastrophe | N54: yes | O54: jev_quilt/engine.py:93-100
B55: jev-quilt | C55: substrate | D55: jev-quilt-P11 | E55: 1 | F55: mechanism | G55: wake = replay book, then decide | H55: A cell woken by a delta first replays its bookkeeper (wake_state catch-up) before any decision — Law 4: replay equals live. | I55: bookkeeper, delta | J55: caught-up state, then decision | K55: wake_state() precedes backend resolution in _wake | L55: precondition | M55: deciding on a stale book would fork the cell from its own history | N55: yes | O55: jev_quilt/engine.py:102-104
B56: jev-quilt | C56: substrate | D56: jev-quilt-P12 | E56: 1 | F56: mechanism | G56: predictor pre-commit (feeling under the ledger) | H56: If the cell carries a predictor, it predicts BEFORE deciding, so the booked receipt binds feeling and fact in one hash — JEPA's slot, v0 the exact MeanPredictor. | I56: cell.predictor | J56: pre-committed prediction in the receipt | K56: predictor exception -> pred=None (feeling is optional, never fatal) | L56: postcondition | N56: yes | O56: jev_quilt/engine.py:106-115
B57: jev-quilt | C57: substrate | D57: jev-quilt-P13 | E57: 2 | F57: policy | G57: backend resolution ladder | H57: resolve_backend maps auto -> q16 (always available) -> openjev-local (if reachable) -> typesafe-api (if TYPESAFE_API_KEY): exactness first, cloud last. | I57: cell.backend | J57: concrete BackendDecision source | K57: unknown backend refused at Cell construction | L57: admission | N57: yes | O57: jev_quilt/engine.py:53-56; jev_quilt/cell.py:53-54
B58: jev-quilt | C58: substrate | D58: jev-quilt-P14 | E58: 4 | F58: evidence | G58: Bookkeeper append-only WAL | H58: Per-cell append-only log of Receipt(tick, state_hash, delta_hash, decision_kind, payload_hash, payload) — the memory is the book; registration wires one per cell (or the honest NullBookkeeper). | I58: tick, state hash, delta, decision | J58: appended Receipt | K58: replay == live (suite test_replay_determinism) | L58: postcondition | N58: yes | O58: jev_quilt/bookkeeper.py:46-53; jev_quilt/engine.py:48-51
B59: jev-quilt | C59: substrate | D59: jev-quilt-P15 | E59: 0 | F59: substrate | G59: fnv1a-64 over UTF-8 bytes | H59: The shared hash: raw BYTES (never str iteration/ord()) so a Rust receipt and a Python receipt for the same residue agree, non-ASCII included — the same algorithm as the rate limiter, hermit WAL and Rust substrate. | I59: bytes | J59: 64-bit hash | K59: cross-language agreement on identical residues (fnv1a reference-vector suite) | L59: invariant | M59: hashing str directly would fork Python from Rust receipts | N59: yes | O59: jev_quilt/bookkeeper.py:33-43
B60: jev-quilt | C60: substrate | D60: jev-quilt-P16 | E60: 4 | F60: evidence | G60: receipt sha binds the residue text | H60: sha() re-derives payload_hash from the retained payload when present, so editing the payload alone breaks replay; empty payload keeps the historical formula — back-compat pinned byte-for-byte. | I60: Receipt fields, payload | J60: chain hash over tick|state|delta|kind|payload_hash | K60: payload edit without hash edit -> replay mismatch (tamper is loud) | L60: seal | N60: yes | O60: jev_quilt/bookkeeper.py:86-100
B61: jev-quilt | C61: substrate | D61: jev-quilt-P17 | E61: 4 | F61: evidence | G61: typed uncapped decision fields (G20a) | H61: Decision-bearing identity (dispatch_id, runner, key, correct, base_verdict, answer) rides as real dataclass fields, never JSON, never sliced by the 200-char payload render budget — identity never floats even in the book. | I61: typed decision fields | J61: \x1f-delimited canonical decision_bytes extending the sha preimage only when set | K61: all-None fields -> empty bytes -> historical preimage byte-identical (additive pin change only) | L61: invariant | M61: a render budget evicting a dispatch id would break routing accountability (the C9 fail-open class) | N61: yes | O61: jev_quilt/bookkeeper.py:55-84
B62: jev-quilt | C62: substrate | D62: jev-quilt-P18 | E62: 2 | F62: policy | G62: book() refuses what it cannot carry exactly | H62: A booking with a non-str/bool typed field, or a value containing the reserved \x1f delimiter, raises rather than silently rounds (Law 6 clause iii: booked = foldable). | I62: book() call | J62: Receipt or raise | K62: raise-on-unrepresentable beats round-and-continue | L62: admission | M62: silent rounding of a decision field is exactly the fail-open class G20a closed | N62: yes | O62: jev_quilt/bookkeeper.py:13-17
B63: jev-quilt | C63: substrate | D63: jev-quilt-P19 | E63: 1 | F63: mechanism | G63: NullBookkeeper honesty | H63: Cells with bookkeeper=False still decide — they just forget: book() no-ops, replay() returns None, verify() returns True, wake_state reports zero booked ticks; forgetting is a declared mode, not a silent omission. | I63: cell.bookkeeper flag | J63: forgetting backend | K63: wake_state honestly reports booked_ticks: 0, chain: None | L63: invariant | M63: a pretending bookkeeper (fake verify) would be worse than an empty one | N63: yes | O63: jev_quilt/engine.py:21-26
B64: jev-quilt | C64: substrate | D64: jev-quilt-P20 | E64: 3 | F64: interface | G64: polyformal ports with honest verification labels | H64: The five laws re-exist in Rust (exact Q16 with no float constructor, overflow = None refusal, fnv1a-chained bookkeeper — 13 cargo tests green per README), Mercury (chain_valid/2, labeled UNVERIFIED — no mmc) and Haskell (phantom-typed Lattice/Proj, UNVERIFIED — no ghc): one substrate, several tongues, each labeled with its actual verification status. | I64: kernel semantics | J64: Rust / Mercury / Haskell sources | K64: UNVERIFIED is printed where no toolchain ran — do not write counts, run the suites | L64: admission | M64: claiming unverified ports as tested would violate the house law | N64: yes | O64: README.md:194-203
B65: quilt-qcells | C65: substrate | D65: quilt-qcells-P01 | E65: 2 | F65: policy | G65: primitive inventory + sugar decomposition at append | H65: Exactly nine primitive ops {init, m, x, h, rx, rz, cx, crx, swap} may enter a ledger; y/z/ry/t sugar decomposes at append time and NEVER enters (SUGAR_OPS is the refusal set). | I65: op calls on CellCircuit | J65: primitive rows only | K65: P2: only primitive ops in BIND rows across all 16 ledgers | L65: admission | M65: a sugar op in a ledger would break the replay contract | N65: yes | O65: qcells.py:108-111, 516-525
B66: quilt-qcells | C66: substrate | D66: quilt-qcells-P02 | E66: 0 | F66: substrate | G66: canonical JSON encoding (C1) | H66: json.dumps(sort_keys=True, separators, ensure_ascii) as UTF-8 — stable, portable, diffable; every non-canonical byte is a parse refusal. | I66: row dict | J66: canonical bytes | K66: parse_ledger: canon(obj) != line -> 'row %d is not in canonical form' | L66: invariant | N66: yes | O66: qcells.py:127-130, 336-350
B67: quilt-qcells | C67: substrate | D67: quilt-qcells-P03 | E67: 0 | F67: substrate | G67: row shape + id derivation (C2) | H67: Row = {seq, op, kind, args, prev}; id = fnv1a-64 over the canonical body WITHOUT the id field; exported JSONL lines are self-contained and independently recomputable. | I67: seq, op, kind, args, prev | J67: row id (16 hex chars) | K67: id mismatch -> 'content tampered or id forged' at that row | L67: seal | N67: yes | O67: qcells.py:137-140, 382-385
B68: quilt-qcells | C68: substrate | D68: quilt-qcells-P04 | E68: 0 | F68: substrate | G68: single linear chain from genesis (C3) | H68: One chain over ALL rows in append order (the only reading satisfying both the gate-sub-chain pin and the PROOF-section pin without forking); genesis prev = 0x0000000000000000 per fleet WAL convention. | I68: rows | J68: prev-linked chain | K68: verify_ledger walks prev == running id from GENESIS; break named at the exact row | L68: conservation | M68: a forked or edited chain breaks every downstream link by construction | N68: yes | O68: qcells.py:28-33, 99-106, 365-391
B69: quilt-qcells | C69: substrate | D69: quilt-qcells-P05 | E69: 0 | F69: substrate | G69: fnv1a-64 (C4) | H69: Standard FNV-1a 64-bit (offset 0xcbf29ce484222325, prime 0x100000001b3), lowercase 16-hex rendering — the fleet's WAL hash. | I69: bytes | J69: 64-bit hash string | N69: yes | O69: qcells.py:118-124
B70: quilt-qcells | C70: substrate | D70: quilt-qcells-P06 | E70: 4 | F70: evidence | G70: LINK boundary row with simulator pin | H70: One circuit-boundary cell at open carries (circuit, simulator pin, shots plan); the pin is sha256 of the vendored micromoth.py because the module exposes no version — the oracle itself is bound into the ledger. | I70: num_qubits, num_clbits, name, shots_plan, simulator_sha256 | J70: LINK row | K70: conformance refuses if vendored micromoth.py sha256 != pinned bbd10ac2... (fail-closed) | L70: precondition | M70: a silently swapped oracle would invalidate every replay comparison | N70: yes | O70: qcells.py:37-40, 148-160; conformance.py:54, 125-127
B71: quilt-qcells | C71: substrate | D71: quilt-qcells-P07 | E71: 1 | F71: mechanism | G71: BIND gate rows from actual circuit tuples | H71: Every gate application emits a BIND {kind:gate, args:{op, qubits, theta?}} derived from the wrapped circuit's real data tuples (sync-based emission), so the ledger is faithful to the circuit by construction; init is a BIND with its payload pinned by sha256, never inlined into VIEWs. | I71: wrapped QuantumCircuit data | J71: BIND rows | K71: emission happens on _sync from qc.data — no parallel hand-maintained history | L71: invariant | M71: a hand-written row diverging from the circuit would fail P1 replay equality | N71: yes | O71: qcells.py:41-44, 459-479
B72: quilt-qcells | C72: substrate | D72: quilt-qcells-P08 | E72: 1 | F72: mechanism | G72: TICK layering (qubit-disjoint greedy) | H72: The gate chain is partitioned into qubit-disjoint layers in append order; a TICK closes each layer; depth = number of TICKs; TICK is monotonic — rows append even when the state returns home (the x*x nuance). | I72: gate rows | J72: TICK rows, depth | K72: TICK tracks BIND gate rows only ('m' readouts are records, not gates) | L72: postcondition | N72: yes | O72: qcells.py:57-63, 230-247
B73: quilt-qcells | C73: substrate | D73: quilt-qcells-P09 | E73: 1 | F73: mechanism | G73: EFFECT readout vs collapse split | H73: The honest event split, receipted: (a) readout = the ('m', q, b) primitive — records wiring, mutates nothing, never collapses; (b) collapse = one cell per shot outcome {shot, outcome, seed}, minted only at sampling. | I73: measure calls, shot outcomes | J73: EFFECT rows of kind readout | collapse | K73: readout rows never mutate gate cells | L73: invariant | M73: calling 'm' a collapse would be physics LARP receipted as dishonest | N73: yes | O73: qcells.py:45-53
B74: quilt-qcells | C74: substrate | D74: quilt-qcells-P10 | E74: 2 | F74: policy | G74: unsealed sampling is minted UNSEALED and excluded | H74: seed=null collapse rows are EFFECT/UNSEALED — the design's honest determinism hole: they are kept, labeled, and excluded from every determinism claim, and their disagreement is itself a proven negative control (4 unsealed runs disagree). | I74: sampling without seed | J74: EFFECT/UNSEALED rows | K74: determinism claims (P4) cover only the 15/15 sealed circuits | L74: admission | M74: claiming determinism over unseeded sampling would be the named lie | N74: yes | O74: qcells.py:50-53; README.md:50-52; verdict.md P4 (15/15 sealed)
B75: quilt-qcells | C75: substrate | D75: quilt-qcells-P11 | E75: 3 | F75: interface | G75: VIEW records the view, digest only | H75: A VIEW row records which view was taken (get, digest, shots?, seed?, counts?); statevector and probabilities are never inlined — only their digests. | I75: view call + digest | J75: VIEW row | K75: view digests re-derive by replay (P1) | L75: postcondition | N75: yes | O75: qcells.py:54-56, 274-280
B76: quilt-qcells | C76: substrate | D76: quilt-qcells-P12 | E76: 3 | F76: interface | G76: PROOF rounded-amplitude witness | H76: A PROOF row is a statevector witness at the current TICK: amplitude pairs rounded to declared precision, sha256-pinned as a digest, verifiable by replay — exact-amplitude witnesses are honestly NOT claimed. | I76: statevector, precision | J76: PROOF row {precision, digest} | K76: sha256(canon(rounded)) == row digest | L76: seal | M76: digest-pinned witnesses prove replay equality, not exact amplitudes (receipted limit) | N76: yes | O76: qcells.py:64-66, 281-287; README.md:48-49
B77: quilt-qcells | C77: substrate | D77: quilt-qcells-P13 | E77: 2 | F77: policy | G77: FORGET tombstone append | H77: Erasure is a receipt, not an excision: the FORGET row names erased collapse ids; the chain is never edited (deleting rows would break every downstream link and make the ledger lie about its own history). | I77: collapse rows to erase, reason | J77: FORGET row | K77: forget with nothing pending raises LedgerError (refusing an empty erasure receipt) | L77: conservation | M77: physical excision would destroy the tamper-evidence the mapping exists for | N77: yes | O77: qcells.py:67-76, 288-306
B78: quilt-qcells | C78: substrate | D78: quilt-qcells-P14 | E78: 3 | F78: interface | G78: serving surface filters tombstones | H78: collapse_records(serve=True) returns non-tombstoned collapse rows: counts stay retained (VIEW), individual shots become FORGET-table — retrieval semantics layered over an immutable chain. | I78: collapse rows, FORGET set | J78: served records | K78: tombstoned ids filtered when serve=True | L78: postcondition | N78: yes | O78: qcells.py:308-319
B79: quilt-qcells | C79: substrate | D79: quilt-qcells-P15 | E79: 4 | F79: evidence | G79: verify_ledger fail-closed localization | H79: Recompute the fnv1a-64 chain from genesis over exported bytes; return (False, seq, reason) on the FIRST violated row — content tamper, forged id, prev break, sequence break, non-canonical form, unknown opcode, truncation. | I79: ledger bytes | J79: (ok, bad_seq, reason) | K79: P3: single-byte tamper of 4254/4254 rows (id-flip, kind-flip, prev-flip x every row of every ledger) detected at exactly the tampered row | L79: postcondition | N79: yes | O79: qcells.py:353-391; verdict.md P3
B80: quilt-qcells | C80: substrate | D80: quilt-qcells-P16 | E80: 4 | F80: evidence | G80: out-of-band anchor check | H80: check_anchor(data, tip, row_count) enforces the published (tip, rows) pair — the honestly-declared limit that a hash chain alone cannot detect tail truncation or a well-formed tail extension. | I80: ledger bytes, published tip, published row count | J80: anchor verdict | K80: row count and tip must equal the anchored pair else 'tail added or removed' | L80: postcondition | M80: the forged-tail and truncated-tail negative controls prove the chain passes where only the anchor catches | N80: yes | O80: qcells.py:394-408; verdict.md negative controls
B81: quilt-qcells | C81: substrate | D81: quilt-qcells-P17 | E81: 1 | F81: mechanism | G81: rebuild_from_rows (the ledger is the circuit) | H81: Reconstruct a QuantumCircuit from ledger rows ONLY: BIND/gate rows re-emit primitives, EFFECT/readout re-issues measure, LINK supplies (n, m, name); the rebuilt circuit's data equals the wrapped original's data. | I81: ledger rows | J81: QuantumCircuit | K81: P1: replay == oracle exactly (rebuilt data == wrapped data, statevector ==, sealed counts ==) across 16/16 circuits | L81: postcondition | M81: rows carrying sugar or hand-forged args would fail simulate()-equality | N81: yes | O81: qcells.py:413-457
B82: quilt-qcells | C82: substrate | D82: quilt-qcells-P18 | E82: 2 | F82: policy | G82: initialize refusal after first gate | H82: initialize() is refused once any gate exists — re-initializing would clear the program out from under the chain; measure_all() and circuit __add__ are deliberately not wrapped (declared scope). | I82: initialize call, existing gates | J82: refusal (LedgerError) | K82: any existing gate row -> refuse | L82: admission | M82: a mid-chain re-init would orphan every prior row's meaning | N82: yes | O82: qcells.py:86-88, 481-489
B83: quilt-qcells | C83: substrate | D83: quilt-qcells-P19 | E83: 4 | F83: evidence | G83: registration seals over the code that runs | H83: conformance --register seals claims PENDING plus sha256+mtime+size of qcells.py / conformance.py / micromoth.py BEFORE runs; every run re-verifies and refuses (exit 2) if the code moved — the code that ran is the code that was sealed. | I83: source files, registration.json | J83: seal verdict | K83: sha256 equal AND |mtime - sealed| <= 1.0s AND size equal, else FATAL refuse | L83: seal | M83: VERIFIED LIVE: stale mtime seals correctly refused this workspace's normalized timestamps — the refusal is the mechanism working | N83: yes | O83: conformance.py:88, 118-127
B84: quilt-qcells | C84: substrate | D84: quilt-qcells-P20 | E84: 4 | F84: evidence | G84: negative controls proving the detection boundary | H84: Five controls: forged tail extension (chain passes, anchor catches), dropped middle row (sequence break), truncated tail (anchor count catches), fully re-forged chain with doctored init payload (anchor AND payload sha pin fire), unsealed sampling disagreement — the map of what is and is not detectable. | I84: tampered ledgers | J84: 5/5 expected detections | K84: each control must be caught by the named mechanism, and the unsealed hole must be real | L84: postcondition | N84: yes | O84: verdict.md:39-44; conformance.py:483-490
B85: quilt-qcells | C85: substrate | D85: quilt-qcells-P21 | E85: 4 | F85: evidence | G85: receipt chain over conformance itself | H85: The conformance run seals its own results into a 21-row fnv1a-64 receipt chain (tip 73583aaef12b1d4d) with byte-identical determinism across full runs and no wall-clock values in receipts. | I85: conformance results | J85: receipts/conformance.jsonl + summary.json | K85: two full runs produce byte-identical receipts (no wall-clock leakage) | L85: seal | M85: a timestamp in receipts would break the byte-identical crown | N85: yes | O85: verdict.md:45-47; receipts/summary.json
B86: jev-garden | C86: garden | D86: jev-garden-P01 | E86: 0 | F86: substrate | G86: hex lattice substrate | H86: 61-cell hex lattice radius 4; hexDist is the axial distance law; every context maps into exactly one cell. | I86: radius (default 4) | J86: lattice cell keys 'q,r' | K86: cell count == 61 at radius 4 (axial formula 3r^2+3r+1) | L86: invariant | M86: an off-lattice coordinate would mis-map; prevented because contextCell indexes the built lattice modulo 61 | N86: yes | O86: src/field.mjs:L14-L28
B87: jev-garden | C87: garden | D87: jev-garden-P02 | E87: 0 | F87: substrate | G87: canonical byte discipline | H87: sorted-key canonicalJSON, sha256Hex, fnv1a64 (fleet chain basis), r6 epoch quantisation, and a LABELED LCG fallback stream — no wall-clock, no Math.random anywhere. | I87: any JS value / string / seed hex | J87: canonical strings, hashes, deterministic uniforms | K87: no wall-clock or Math.random in any deterministic path (header law of canon.mjs) | L87: invariant | M87: byte-nondeterministic weaves would break the JS==Python twin claim (P-G5) | N87: yes | O87: src/canon.mjs:L1-L49
B88: jev-garden | C88: garden | D88: jev-garden-P03 | E88: 1 | F88: mechanism | G88: context-to-cell pre-registered mapping | H88: contextCell = lattice[fnv1a64(canonical context string) % 61] — the DESIGN.md §4 pre-registered mapping from judgment context to lattice coordinate. | I88: context string | J88: cell key | K88: same context string always yields the same cell (pre-registered, deterministic) | L88: invariant | M88: re-registering the mapping after growth would invalidate all accumulated memory | N88: yes | O88: src/field.mjs:L30-L35
B89: jev-garden | C89: garden | D89: jev-garden-P04 | E89: 1 | F89: mechanism | G89: deform (JEV soft emit) | H89: every judgment event appends an alpha=0.4-weighted (gamma,eta,delta) deformation to the mapped cell; never a definite token; delta defaults to the creative-band centre 0.5. | I89: contextStr, gamma, surprise, tag | J89: journal row {kind:'deform'}, mutated cell accumulators | K89: deform never emits a definite token — only (gamma,eta,delta) masses | L89: invariant | M89: a hard write here would collapse the wave and erase the non-collapsing claim | N89: yes | O89: src/field.mjs:L48-L68
B90: jev-garden | C90: garden | D90: jev-garden-P05 | E90: 1 | F90: mechanism | G90: observe — the only collapse | H90: an observed outcome (receipt label, teacher answer, human REVIEW) is the only place supervision exists; it appends an 'observe' row and increments the per-context op aggregate. | I90: contextStr, op, source | J90: journal row {kind:'observe'}, observed aggregate | K90: observations are the only collapses (smoke-asserted) | L90: invariant | M90: supervision leaking in anywhere else would make training unauditable | N90: yes | O90: src/field.mjs:L70-L81
B91: jev-garden | C91: garden | D91: jev-garden-P06 | E91: 4 | F91: evidence | G91: hash-chained growth journal | H91: append-only journal; each row_hash = sha256(canonicalJSON([prev, row])) from GENESIS; verifyJournal replays and names the exact failing seq. | I91: journal rows | J91: chain tip, verification verdict {ok, at} | K91: verifyJournal ok after clean run; tamper detected AND localized at exact row (selftest rows) | L91: seal | M91: a silent rewrite would forge the field's history | N91: yes | O91: src/field.mjs:L83-L102; tests/selftest.mjs:L65-L75
B92: jev-garden | C92: garden | D92: jev-garden-P07 | E92: 1 | F92: mechanism | G92: rhizome prior (amplitude-weighted vote) | H92: pure, non-mutating sense-time aggregate: observed op votes weighted by cell gamma/(aSum)/(1+hexDist) within radius 2; uniform fallback when no mass. | I92: contextStr, radius | J92: op probability table | K92: total<=0 falls back to uniform 1/7 (no crash, no invention) | L92: postcondition | M92: empty memory must degrade to honest uniform, not garbage | N92: yes | O92: src/field.mjs:L104-L139
B93: jev-garden | C93: garden | D93: jev-garden-P08 | E93: 1 | F93: mechanism | G93: counted memory prior (A1 addendum) | H93: priorCounted: add-1 smoothed exact-context counts, falling back to the global observed distribution — the payload the P-G2d +13.41pp and the A9/A10/A12 fresh-serve laws ride on. | I93: contextStr | J93: op probability table | K93: unseen context uses the global observed distribution, never zeros | L93: postcondition | M93: exact-context memorisation does not transfer across circuit families (P-G2b FAIL of record) | N93: yes | O93: src/field.mjs:L141-L160
B94: jev-garden | C94: garden | D94: jev-garden-P09 | E94: 3 | F94: interface | G94: sense table serialization (weave-2) | H94: the compact order-free serialization of everything prior() consumes — cells with >=1 observed context carry r6(G), r6(aSum); supervision aggregate sorted bytewise — so the weave artifact can carry the living-memory arm. | I94: rhizome state | J94: {cells, observed} serializable table | K94: byte-deterministic under canonicalJSON (sorted contexts, sorted ops, r6) | L94: invariant | M94: nondeterministic serialization would break P-G5 cross-substrate identity | N94: yes | O94: src/field.mjs:L181-L199
B95: jev-garden | C95: garden | D95: jev-garden-P10 | E95: 1 | F95: mechanism | G95: qthe prototype arm | H95: growth is adding prototype cells keyed op|yR|yI (integer split-channel QTHE aggregation) — no gradients anywhere; judgment = distance-weighted prototype vote blended with the abstain wormhole. | I95: train samples (tokens, label) | J95: prototype list + wormhole; judgeQthe probability table | K95: zero-score tie falls back to honest uniform (tie flag returned) | L95: postcondition | M95: overflow impossible — integers packed into tau:2+d:6 bytes | N95: yes | O95: src/heads.mjs:L10-L46
B96: jev-garden | C96: garden | D96: jev-garden-P11 | E96: 1 | F96: mechanism | G96: hash-arm SGD head | H96: softmax over 2^11 hashed n-gram buckets trained by zero-dep JS SGD with sealed HYP (lr 0.5, epochs 12, wd 1e-4, clip 5) — torch-shaped, torch-free, epoch-quantised weights. | I96: train samples | J96: W[7][2048], b[7]; judgeHash probability table | K96: deterministic: zero-init weights, no RNG (selftest 'trainHash deterministic') | L96: invariant | M96: float drift across substrates — contained by r6 epoch quantisation | N96: yes | O96: src/heads.mjs:L48-L85
... B135: jeviter | C135: garden | D135: jeviter-P24 | E135: 3 | F135: interface | G135: CLI + TUI surfaces | H135: zero-dep command surfaces: tail (file), follow (URL with --k), scan (verify chain + name the silence pattern), digest (stdin), tui (live ANSI instrument panel rendering silences as data). | I135: argv | J135: iterator/scan/TUI sessions | K135: scan names the silence pattern; TUI renders quiet as data, not as failure costume (test-pinned) | L135: postcondition | M135: a TUI that renders quiet as an error would invert the doctrine | N135: yes | O135: README.md:L43-L50; README.md:L66-L75
B136: exoj | C136: garden | D136: exoj-P01 | E136: 0 | F136: substrate | G136: hex geometry | H136: axial hexDist = (|dq|+|dq+dr|+|dr|)/2 and hexRing neighbourhood enumeration — the metric all locality (rings, distance-weighted priors) hangs on. | I136: axial coordinates | J136: distance / ring coordinates | M136: a wrong axial distance would corrupt every locality-dependent statistic | N136: yes | O136: core.mjs:L50-L62
B137: exoj | C137: garden | D137: exoj-P02 | E137: 0 | F137: substrate | G137: content-addressing primitives | H137: canonicalJSON (sorted keys, no undefined), sha256Hex, and chainHash(row, prev) = sha256(canonicalJSON([prev, row-without-hash])) — the exact chain basis the fleet shares. | I137: any value / rows | J137: canonical strings, hashes | K137: key order can never change a hash (sorted canonical form) | L137: invariant | M137: non-canonical serialization would let reordered keys forge different proof objects | N137: yes | O137: core.mjs:L32-L46
B138: exoj | C138: garden | D138: exoj-P03 | E138: 0 | F138: substrate | G138: cell state bundle | H138: Cell carries gamma/eta/delta (seed view), delta_override (observe-pinned definite), strength, frags (content-addressed identity fragments), programs, touched, prob_mass, plus the ledger-policy accumulators G/E/D/aSum/n. | I138: (q, r) coordinates | J138: cell with default eta=1, delta=0.5, prob_mass=1 (fully open) | K138: a never-touched cell is fully open: prob_mass = 1.0, gamma = 0 | L138: invariant | M138: a closed-by-default cell would fake prior knowledge | N138: yes | O138: core.mjs:L69-L79
B139: exoj | C139: garden | D139: exoj-P04 | E139: 1 | F139: mechanism | G139: soft_write (seed reference) | H139: convex blend (1-alpha)*old + alpha*new for each amplitude, alpha=0.4; strength = max(strength, gamma); prob_mass relaxes upward 0.98*p + 0.02; order-DEPENDENT by design — the verbatim seed semantics kept as one honest arm. | I139: (g, e, d, alpha) | J139: mutated cell view state | K139: alpha fixed at 0.4 default; write is convex (no overshoot of the targets) | L139: invariant | M139: order-dependence is why e_x1 crowned the ledger policy — retained as the reference arm, not deleted | N139: yes | O139: core.mjs:L82-L89
B140: exoj | C140: garden | D140: exoj-P05 | E140: 1 | F140: mechanism | G140: accumulate (ledger naturality policy) | H140: commutative alpha-weighted accumulation into G/E/D/aSum — a multiset union of write targets; any permutation of the same write multiset lands bit-near-identically (float residual ~1e-15, receipted in e_x1). | I140: (g, e, d, alpha) | J140: mutated accumulators only | K140: permutation of the same writes changes nothing beyond ~1e-15 float noise | L140: invariant | M140: parallel observers writing in different orders would disagree — the exact naturality failure E-X1 killed | N140: yes | O140: core.mjs:L91-L99
...

Sheet Gates
B2: Gates the jevs swept (401 gates, rules pre-registered)
B4: work | C4: part_id | D4: layer | E4: layer_name | F4: gate_kind | G4: sweep_verdict | H4: gate
B5: qthe | C5: qthe-P01 | D5: 0 | E5: substrate | F5: postcondition | G5: OPEN | H5: 256/256 values round-trip exact AND 256 distinct packed outputs (gate G1)
B6: qthe | C6: qthe-P02 | D6: 0 | E6: substrate | F6: invariant | G6: OPEN | H6: PSI === [0, 1, -1, 'i'] asserted by G1
B7: qthe | C7: qthe-P03 | D7: 0 | E7: substrate | F7: postcondition | G7: OPEN | H7: hand-computed fixtures exact and every output Number.isInteger (G4: row0 [A10,R4,I6,G63] x xs[2,3,5,7] -> {re:8, im:30})
B8: qthe | C8: qthe-P04 | D8: 0 | E8: substrate | F8: precondition | G8: OPEN | H8: w, h positive integers else RangeError
B9: qthe | C9: qthe-P05 | D9: 1 | E9: mechanism | F9: invariant | G9: OPEN | H9: exactly SLOT_COUNT=64 slots; write outside [0,64) throws RangeError
B10: qthe | C10: qthe-P06 | D10: 1 | E10: mechanism | F10: postcondition | G10: OPEN | H10: lone Abstain cell never twins after its own first write; every event term === log2(3) exactly (G5 schedule)
B11: qthe | C11: qthe-P07 | D11: 1 | E11: mechanism | F11: postcondition | G11: OPEN | H11: totalWrites = 12 after the G5 6-tick twin fixture
B12: qthe | C12: qthe-P08 | D12: 2 | E12: policy | F12: budget | G12: OPEN | H12: the SPEC prices sigma as OPEN: only the sweep {log2(3), 0.5, 1, 2, 4} decides (C3); the gifted 'proof' is receipted as decorative
B13: qthe | C13: qthe-P09 | D13: 1 | E13: mechanism | F13: invariant | G13: OPEN | H13: tick mutates in place and returns the same substrate with synchronous-exact semantics
B14: qthe | C14: qthe-P10 | D14: 1 | E14: mechanism | F14: invariant | G14: OPEN | H14: G2 full-tick exhaustion: 3840/3840 cell-updates in bounds with tau preserved
B15: qthe | C15: qthe-P11 | D15: 1 | E15: mechanism | F15: postcondition | G15: OPEN | H15: 2304/2304 exhausted states x 9 pressures stay in [0,63] (G2a — the Coq theorem restated by exhaustion)
B16: qthe | C16: qthe-P12 | D16: 1 | E16: mechanism | F16: invariant | G16: OPEN | H16: G2: tau preserved EXACTLY on 3840/3840 updates
... B405: external-scouts | C405: external-scouts-P16 | D405: 2 | E405: policy | F405: precondition | G405: OPEN | H405: an unanchored pillar must carry pre-registered claims, not borrowed citations

Sheet Ideas
B2: Core ideas, decomposed (145 ideas)
B4: work | C4: idea_id | D4: name | E4: statement | F4: decomposed_into_parts
B5: qthe | C5: qthe-I1 | D5: The packed byte primitive (data is geometry, control is physics) | E5: A single byte splits into two planes: 6 bits of spatial amplitude d in [0,63] and 2 bits of timbre tau over {Ground, Attract, Repel, Abstain}, with the operator map Psi = [0, +1, -1, 'i'] and an exact split-channel vector pass — no floats anywhere in LAYER 0. | F5: qthe-P01, qthe-P02, qthe-P03, qthe-P04
B6: qthe | C6: qthe-I2 | D6: The 64-slot wormhole table as compile-time blueprint | E6: Abstain cells read/write a fixed 64-slot table: a twin hit on a different (x,y) with nonzero resonance injects resonance*sigma into the pressure (the imaginary channel entering through the only free degree of freedom), writes are last-writer-wins, and nobody resonates with their own write. | F6: qthe-P05, qthe-P06, qthe-P07, qthe-P08
B7: qthe | C7: qthe-I3 | D7: Deterministic Moore-8 tick with frozen timbre | E7: One synchronous, toroidal, double-buffered tick: neighbors read from the pre-tick snapshot, Attract/Repel accumulate signed d into pressure, data moves by a pure saturation rule toward 63 or 0, and tau never changes inside tick — same substrate plus same tick count is byte-identical, always. | F7: qthe-P09, qthe-P10, qthe-P11, qthe-P12, qthe-P13, qthe-P14, qthe-P16
B8: qthe | C8: qthe-I4 | D8: Pre-registered gates and stone receipts with honest failure | E8: Every gate's prediction is written before the run, observed numbers seal into a stone-v1 chain, a wrong prediction (G4's hand-arithmetic error) is kept forever by letter with the correction checked post-hoc, and an independent two-reader proves the chain fails closed at the tampered row. | F8: qthe-P17, qthe-P18, qthe-P19, qthe-P20
B9: quilt-jepa | C9: quilt-jepa-I1 | D9: The grid IS the latent space | E9: Each of the 16x16 cells holds its own 4-dim latent; a per-cell context encoder Wc and predictor Wp learn to predict the cell's own latent future against an EMA target encoder (tau, stop-gradient) — no pixel reconstruction anywhere. | F9: quilt-jepa-P03, quilt-jepa-P04, quilt-jepa-P05, quilt-jepa-P06, quilt-jepa-P07
B10: quilt-jepa | C10: quilt-jepa-I2 | D10: Conservation-law surprise mesh | E10: A double-buffered Perona-Malik anisotropic diffusion (lambda=0.2 <= 0.25 stability bound) moves prediction-surprise across the mesh as pairwise symmetric exchange: energy is never minted nor destroyed and variance contracts. | F10: quilt-jepa-P09, quilt-jepa-P10, quilt-jepa-P11, quilt-jepa-P12
B11: quilt-jepa | C11: quilt-jepa-I3 | D11: Determinism as the foundation of every claim | E11: The world is xorshift32-seeded with no Math.random, so twin runs are byte-identical; every experiment is registered and sealed BEFORE the run, the run re-verifies the seal at startup fail-closed, and a stone chain + verifier make tampering loud. | F11: quilt-jepa-P01, quilt-jepa-P13, quilt-jepa-P14, quilt-jepa-P15
B12: quilt-jepa | C12: quilt-jepa-I4 | D12: Bit-exact claim re-binding across the depth ladder | E12: Rounds 4..10 form a ladder where every carried metric must re-bind bit-exactly (run4 29/29, run5 92/92, cross-round metric shas) while only new claims are measured fresh — concentration statistics, not global means (design law (b)) — and honest FAILs (DOSE10, SAT10, DIP10) are carried as verdicts, not hidden. | F12: quilt-jepa-P16, quilt-jepa-P17, quilt-jepa-P18
B13: jev-quilt | C13: jev-quilt-I1 | D13: Identity never floats | E13: A cell is identified by integer quilt coordinates (k, s) plus declared type; values that are identities use the exact Q16 rational codec (num:int64, den:int64, always coprime) and floats are display-only projections — from_float refuses anything not representable rather than silently rounding. | F13: jev-quilt-P01, jev-quilt-P05, jev-quilt-P06
B14: jev-quilt | C14: jev-quilt-I2 | D14: Hooks eat deltas, not values | E14: A cell subscribes to a sibling's CHANGE (never a polled value): deltas below the hook's deadband floor are silent, a when-predicate can decline deltas whose shape isn't the hook's, and a broken predicate must never silence the fabric — every wake or silence is logged as a WakeResult. | F14: jev-quilt-P02, jev-quilt-P07, jev-quilt-P08, jev-quilt-P09, jev-quilt-P10
B15: jev-quilt | C15: jev-quilt-I3 | D15: Decide in one pass, project elsewhere; viability is binary | E15: The decider never renders and the renderer never decides (Law 3): a decision passes a binary confidence floor before it may project (Law 5); below the floor the outcome is booked as REJECTED, never projected, and a predictor pre-commits its feeling so the receipt binds feeling and fact in one hash. | F15: jev-quilt-P03, jev-quilt-P04, jev-quilt-P11, jev-quilt-P12
... B149: external-scouts | C149: external-scouts-I5 | D149: the dud channel and the novel part | E149: The continual-learning query returned pure junk (a Toyota production-system PPT, Philippine history, RuneScape gloves, SVN commit diffs) — the second failure of that channel on production-ML phrasing — receipted rather than deleted; consequently growth-from-usage has NO external anchor and is the part the garden builds novel, with pre-registered claims instead of citations. | F149: external-scouts-P15, external-scouts-P16, external-scouts-P17

Sheet Cells
B2: Each work re-rendered as quilt cells (366 cells)
B4: work | C4: cell_id | D4: kind | E4: expr | F4: deps | G4: maps_to_part
B5: qthe | C5: tau | D5: value | E5: c >> 6 (bit 7-6) | F5: byte | G5: qthe-P01
B6: qthe | C6: d | D6: value | E6: c & 0x3F (bit 5-0) | F6: byte | G6: qthe-P01
B7: qthe | C7: psi | D7: formula | E7: PSI[tau] = 0 | +1 | -1 | 'i' | F7: tau | G7: qthe-P02
B8: qthe | C8: vec_re | D8: formula | E8: sum(Attract d*x) - sum(Repel d*x) | F8: d, psi, x | G8: qthe-P03
B9: qthe | C9: vec_im | D9: formula | E9: sum(Abstain d*x) | F9: d, psi, x | G9: qthe-P03
B10: qthe | C10: acc | D10: formula | E10: Moore-8 signed sum of neighbor d (pre-tick snap) | F10: snap | G10: qthe-P10
B11: qthe | C11: twin | D11: listener | E11: slot[d] occupied by other (x,y) with r!=0 -> term = r*sigma | F11: d, wormholes | G11: qthe-P06
B12: qthe | C12: wh_write | D12: program | E12: slot[d] <- {x, y, |acc|+1}; last writer wins | F12: acc, d | G12: qthe-P07
B13: qthe | C13: sigma | D13: value | E13: log2(3) default, swept | G13: qthe-P08
B14: qthe | C14: next_d | D14: formula | E14: p>0 ? min(d+1,63) : p<0 ? max(d-1,0) : d | F14: acc, twin | G14: qthe-P11
B15: qthe | C15: byte_out | D15: formula | E15: (tau << 6) | next_d — tau frozen | F15: tau, next_d | G15: qthe-P12
B16: qthe | C16: trace | D16: formula | E16: traceView(cells) hash per tick | F16: byte_out, wormholes | G16: qthe-P15
B17: qthe | C17: rand_scan | D17: sensor | E17: count of Math.random in kernel === 0 | G17: qthe-P14
B18: qthe | C18: receipt | D18: io | E18: append {gate, pred, observed} to receipts.jsonl | F18: trace | G18: qthe-P18
B19: quilt-jepa | C19: obs | D19: value | E19: wave(x,y,t)*0.5+0.5 + ball bump (clipped) | F19: world.t | G19: quilt-jepa-P02
B20: quilt-jepa | C20: feat | D20: formula | E20: [l, r-l, d-l, l-0.5] per cell | F20: obs | G20: quilt-jepa-P03
B21: quilt-jepa | C21: z_ctx | D21: formula | E21: Wc[c] * feat | F21: feat | G21: quilt-jepa-P04
B22: quilt-jepa | C22: z_pred | D22: formula | E22: Wp[c] * z_ctx | F22: z_ctx | G22: quilt-jepa-P05
B23: quilt-jepa | C23: z_tgt | D23: formula | E23: Wt[c] * feat(t+1) | F23: feat, Wt | G23: quilt-jepa-P06
B24: quilt-jepa | C24: ema | D24: formula | E24: Wt <- 0.999*Wt + 0.001*Wc | F24: z_pred, z_tgt | G24: quilt-jepa-P06
B25: quilt-jepa | C25: loss | D25: formula | E25: mean((z_pred - z_tgt)^2), grads clipped [-1,1] | F25: z_pred, z_tgt | G25: quilt-jepa-P07
B26: quilt-jepa | C26: energy | D26: value | E26: channel-3 per mesh cell | F26: obs | G26: quilt-jepa-P09
B27: quilt-jepa | C27: flux | D27: formula | E27: sum_i lambda * exp(-((mc-ni)^2)/kappaSq) * (e_i - e) | F27: energy | G27: quilt-jepa-P10
B28: quilt-jepa | C28: totals | D28: sensor | E28: {total, variance} over active buffer; variance non-increasing | F28: flux | G28: quilt-jepa-P11
B29: quilt-jepa | C29: surprise_z | D29: formula | E29: percentile-z concentration over sampled cells | F29: totals | G29: quilt-jepa-P12
B30: quilt-jepa | C30: seal | D30: listener | E30: re-verify registration masked-sha + mtime at startup; refuse otherwise | G30: quilt-jepa-P13
B31: quilt-jepa | C31: chain | D31: io | E31: append receipt row; tip = sha(prev:body:id) | F31: loss, surprise_z | G31: quilt-jepa-P14
B32: quilt-jepa | C32: verdict | D32: sensor | E32: scorecard over claims; honest FAILs carried | F32: chain | G32: quilt-jepa-P17
B33: jev-quilt | C33: coord | D33: value | E33: (k, s) integers only — TypeError otherwise | G33: jev-quilt-P01
B34: jev-quilt | C34: q | D34: value | E34: Q16(num, den) coprime; from_float refuses unrepresentable | G34: jev-quilt-P05
B35: jev-quilt | C35: floor | D35: sensor | E35: |delta| >= hook.floor (Q16) else silent_deadband | F35: delta | G35: jev-quilt-P07
B36: jev-quilt | C36: when | D36: sensor | E36: hook.when(state); exception -> True (wake) | F36: state | G36: jev-quilt-P10
B37: jev-quilt | C37: backend | D37: router | E37: auto -> q16 -> openjev-local -> typesafe-api | F37: cell.backend | G37: jev-quilt-P13
B38: jev-quilt | C38: decision | D38: ai | E38: Choice | Score | Noul in one pass | F38: backend, state | G38: jev-quilt-P12
B39: jev-quilt | C39: viable | D39: sensor | E39: confidence > 0.0 (Law 5 binary floor) | F39: decision | G39: jev-quilt-P04
B40: jev-quilt | C40: project | D40: io | E40: Projection(to, as_type) only if viable; else booked REJECTED | F40: viable | G40: jev-quilt-P03
B41: jev-quilt | C41: book | D41: program | E41: append Receipt(tick, state_hash, delta_hash, kind, payload_hash) | F41: decision | G41: jev-quilt-P14
B42: jev-quilt | C42: sha | D42: formula | E42: fnv1a64 over UTF-8 of tick|state|delta|kind|payload_hash[|decision] | F42: book | G42: jev-quilt-P16
B43: jev-quilt | C43: replay | D43: formula | E43: rebuild state from book on wake (replay == live) | F43: sha | G43: jev-quilt-P11
B44: jev-quilt | C44: wake_log | D44: listener | E44: every emit logs WakeResult(woke, reason) | F44: floor, when | G44: jev-quilt-P09
B45: quilt-qcells | C45: link | D45: io | E45: boundary row: circuit + sha256(micromoth.py) pin + shots plan | G45: quilt-qcells-P06
B46: quilt-qcells | C46: gate_row | D46: program | E46: BIND {op, qubits, theta?} from qc.data on sync | F46: link | G46: quilt-qcells-P07
B47: quilt-qcells | C47: sugar | D47: router | E47: y/z/ry/t decompose to primitives at append; never stored | F47: gate_row | G47: quilt-qcells-P01
B48: quilt-qcells | C48: tick | D48: formula | E48: close qubit-disjoint layer; depth++ | F48: gate_row | G48: quilt-qcells-P08
B49: quilt-qcells | C49: effect | D49: listener | E49: readout (wiring) or collapse {shot, outcome, seed|null} | F49: gate_row | G49: quilt-qcells-P09
B50: quilt-qcells | C50: view | D50: formula | E50: digest of statevector/probabilities view | F50: effect | G50: quilt-qcells-P11
B51: quilt-qcells | C51: proof | D51: formula | E51: sha256 of rounded amplitude pairs | F51: view | G51: quilt-qcells-P12
B52: quilt-qcells | C52: forget | D52: program | E52: tombstone append naming erased collapse ids | F52: effect | G52: quilt-qcells-P13
B53: quilt-qcells | C53: id | D53: formula | E53: fnv1a64(canon({seq,op,kind,args,prev})) | F53: gate_row, tick | G53: quilt-qcells-P03
B54: quilt-qcells | C54: prev | D54: value | E54: parent row id; genesis 0000000000000000 | F54: id | G54: quilt-qcells-P04
B55: quilt-qcells | C55: verify | D55: sensor | E55: chain walk from genesis; first violated row | F55: prev, id | G55: quilt-qcells-P15
B56: quilt-qcells | C56: anchor | D56: sensor | E56: (tip, rows) published pair must match | F56: verify | G56: quilt-qcells-P16
B57: quilt-qcells | C57: replay | D57: program | E57: rebuild QuantumCircuit from rows only; simulate() == oracle | F57: anchor | G57: quilt-qcells-P17
B58: jev-garden | C58: g_ops | D58: value | E58: OPS = [LINK,BIND,TICK,EFFECT,VIEW,FORGET,PROOF] | G58: jev-garden-P01
B59: jev-garden | C59: g_cellmap | D59: formula | E59: cell(ctx) = lattice[fnv1a64(ctx) % 61] | F59: g_ops | G59: jev-garden-P03
B60: jev-garden | C60: g_deform | D60: formula | E60: cell.G += 0.4*gamma; cell.E += 0.4*(1-gamma); cell.D += 0.4*delta; cell.aSum += 0.4 | F60: g_cellmap | G60: jev-garden-P04
B61: jev-garden | C61: g_observe | D61: listener | E61: on labeled receipt: journal+={kind:'observe'}; observed[ctx][op]++ (the ONLY collapse) | F61: g_cellmap | G61: jev-garden-P05
B62: jev-garden | C62: g_prior | D62: formula | E62: prior(ctx) = sum_{d<=2} (G/aSum)/(1+d) * opVotes / total (uniform fallback) | F62: g_deform, g_observe | G62: jev-garden-P07
B63: jev-garden | C63: g_hashfeat | D63: formula | E63: hashFeatures(tokens): k=3 window -> 2^11 buckets, L2-normalised | F63: g_ops | G63: jev-garden-P13
B64: jev-garden | C64: g_sgd | D64: formula | E64: W,b <- 12 epochs SGD(lr=0.5, wd=1e-4, clip=5), r6 per epoch | F64: g_hashfeat | G64: jev-garden-P11
B65: jev-garden | C65: g_gate | D65: router | E65: PROMOTE iff min_gain>=+0.02 AND worst_gain>=-0.05; else REVIEW/DISCARD | F65: g_sgd | G65: jev-garden-P16
B66: jev-garden | C66: g_weave | D66: program | E66: weaveIfIdle: diff journal -> train challengers -> gate -> artifact{sha256, journal_tip} | F66: g_gate, g_prior | G66: jev-garden-P17
B67: jev-garden | C67: g_judge | D67: api | E67: judge(state, questions) -> {answers(noul/choice/score), escalate: top.p<0.55, usage} | F67: g_weave | G67: jev-garden-P20
B68: jev-garden | C68: g_budget | D68: router | E68: budget.grant(escalate): spent<cap ? grant : refuse+budget_exhausted (counted) | F68: g_judge | G68: jev-garden-P21
B69: jev-garden | C69: g_teacher | D69: io | E69: teacherJudge -> usage receipt appended to growth journal (fail-closed without key) | F69: g_budget | G69: jev-garden-P23
B70: jeviter | C70: j_k | D70: value | E70: k = 2.0 (default surprise multiplier, per-call overridable) | G70: jeviter-P07
B71: jeviter | C71: j_profile | D71: sensor | E71: profile(text) -> {vowels,cons,digits,sep,other} as Q16 shares | G71: jeviter-P03
B72: jeviter | C72: j_gain | D72: formula | E72: klGain(base, reading) = Σ p·log(p/q) over shared support | F72: j_profile | G72: jeviter-P04
B73: jeviter | C73: j_gainstrict | D73: formula | E73: klGainStrict: vanished/novel mass counts at full weight | F73: j_profile | G73: jeviter-P05
B74: jeviter | C74: j_thresh | D74: formula | E74: threshold = mean(accepted) + k·σ(accepted) (EWMA variant over ALL pulls) | F74: j_k | G74: jeviter-P07
B75: jeviter | C75: j_router | D75: router | E75: next(): seed if no belief; silence if gain<=th; event + belief update if gain>th | F75: j_gain, j_thresh | G75: jeviter-P12
B76: jeviter | C76: j_ledger | D76: listener | E76: ledger.book(state, payload, kind) on EVERY pull outcome; fnv1a64 chain | F76: j_router | G76: jeviter-P09
B77: jeviter | C77: j_scan | D77: formula | E77: scanLedger -> TAMPER/EMPTY/QUIET/ALIVE + admission % | F77: j_ledger | G77: jeviter-P13
B78: jeviter | C78: j_throttle | D78: router | E78: Throttle.call: shed (receipted) vs escalate (fn runs) — ratchet after one admission | F78: j_gainstrict, j_thresh | G78: jeviter-P14
B79: jeviter | C79: j_governor | D79: program | E79: MergeGovernor.consider: seed | merged | merged-divergent(+restLen) | held | F79: j_profile, j_thresh | G79: jeviter-P16
B80: jeviter | C80: j_distill | D80: program | E80: distill: CITATION + DUP + JEV GATE + WELL-FORMEDNESS -> CANON stub | F80: j_throttle, j_ledger | G80: jeviter-P18
B81: jeviter | C81: j_dream | D81: program | E81: consolidateMemory: old WAL tail -> summary + receipt; originals relocated | F81: j_ledger | G81: jeviter-P22
B82: exoj | C82: x_lattice | D82: value | E82: cells = {(q,r) : hexDist(q,r,0,0) <= 4} (61 cells, open by default) | G82: exoj-P08
B83: exoj | C83: x_cell | D83: value | E83: cell = {gamma:0, eta:1, delta:0.5, prob_mass:1, G,E,D,aSum, frags, programs, touched} | F83: x_lattice | G83: exoj-P03
B84: exoj | C84: x_softwrite | D84: formula | E84: softWrite: cell.a = 0.6*cell.a + 0.4*a (seed arm, order-dependent) | F84: x_cell | G84: exoj-P04
B85: exoj | C85: x_accum | D85: formula | E85: accumulate: cell.G += 0.4*g; cell.E += 0.4*e; cell.D += 0.4*d; cell.aSum += 0.4 (commutative) | F85: x_cell | G85: exoj-P05
B86: exoj | C86: x_emit | D86: api | E86: jevEmit(q,r,g,e,d,{backend,tag,program}) -> policy write + frag + chained deform row | F86: x_softwrite, x_accum | G86: exoj-P14
B87: exoj | C87: x_refuse | D87: router | E87: policy='refuse': postG+postE > 1+1e-12 ? chained refusal (counted) : write lands | F87: x_emit | G87: exoj-P13
B88: exoj | C88: x_observe | D88: listener | E88: observe(q,r,definite): prob_mass=0, delta_override=definite, chained observe row — the ONLY collapse | F88: x_cell | G88: exoj-P15
B89: exoj | C89: x_program | D89: program | E89: attachProgram + tick(t): every/at refreshes as alpha=0.2 soft emits tagged program:<id> | F89: x_emit | G89: exoj-P17
B90: exoj | C90: x_sense | D90: sensor | E90: sense(): Sigma, Sigma_normed, max_cell_Sigma, zone, prob_open, counts, chain_tip (pure) | F90: x_accum, x_observe | G90: exoj-P18
B91: exoj | C91: x_project | D91: api | E91: project(observer) -> exoj-projection-v1 slice; appends ZERO rows | F91: x_sense | G91: exoj-P19
B92: exoj | C92: x_save | D92: io | E92: save(path) / ExoJ.load(path): exoj-shell-v1 with cells_raw + full chain + tip | F92: x_sense | G92: exoj-P21
B93: exoj | C93: x_chain | D93: formula | E93: row_hash = sha256(canonicalJSON([prev_tip, row])); verifyChain from EXOJ-GENESIS | F93: x_emit, x_observe, x_refuse | G93: exoj-P09
B94: fleet-seeds | C94: f_seed | D94: io | E94: seeds/*.md -> seedbox hopper (14 charters of record on disk) | G94: fleet-seeds-P01
B95: fleet-seeds | C95: f_charter | D95: formula | E95: README(spawn) = HEADER + seed.verbatim + DOCTRINE(5 laws) + first-lane checklist | F95: f_seed | G95: fleet-seeds-P02
B96: fleet-seeds | C96: f_spawn | D96: program | E96: spawn(seed, slug): scaffold 6 files -> git init -> commit 'charter verbatim' (1 commit) | F96: f_charter | G96: fleet-seeds-P06
B97: fleet-seeds | C97: f_ci | D97: listener | E97: on push: node smoke.mjs -> 'SMOKE OK (n/n)' + exit code | F97: f_spawn | G97: fleet-seeds-P05
B98: fleet-seeds | C98: f_selftest | D98: sensor | E98: --selftest: spawn demo -> smoke green? -> cleanup -> PASS + clean tree | F98: f_spawn, f_ci | G98: fleet-seeds-P07
B99: fleet-seeds | C99: f_lineage | D99: value | E99: seed-grok2.md == exoj charter (byte-for-byte lineage proof) | F99: f_charter | G99: fleet-seeds-P09
B100: fleet-seeds | C100: f_lode | D100: router | E100: scout -> extract -> score -> register(sealed prediction + mine id) -> lane -> fold | G100: fleet-seeds-P11
B101: fleet-seeds | C101: f_validate | D101: formula | E101: lode_validate: schema + hash + append-only, exit 2 fail-closed, tamper self-tests | F101: f_lode | G101: fleet-seeds-P12
B102: fleet-seeds | C102: f_registry | D102: io | E102: registry.jsonl: {set_id, repo, commit, verdict, seal ref, ts} append-only | F102: f_validate | G102: fleet-seeds-P16
...

Sheet Ledger
B2: Timestamped ledgers (append-only; 106 rows)
B4: ts | C4: source | D4: lane | E4: work | F4: event | G4: detail
B5: 2026-10-04T06:59:27Z | C5: gatesweep-66-g.jsonl | D5: 66-g | E5: PRE-REGISTER | F5: rules | G5: {"R1_OPEN":"gate non-empty AND gate_kind non-null -> emit(g=0.75,e=0.25,d=0.50)","R2_SOFT":"gate non-empty AND gate_kind null -> emit(g=0.50,e=0.50,d=0.50)","R3_HOLE":"gate empty/null -> observe(d=0.20) explicit local collapse","R4_SEAL":"gate_kind in {seal,conservation} -> extra emit(g=0.85,e=0.15,d=0.50)","R5_LAYERHOLE":"work missing any layer 0..4 -> observe at that layer cell","R6_THIN":"work with <5 gated parts -> warning emit(g=0.35,e=0.65,d=0.50)","geometry":"work i -> q=(i%7)-3 ; layer L -> r=L-2 ; radius 6 ; policy ledger","backend":"atlas-sweep (deterministic structural judgment; no LLM, no network)"}
B6: 2026-10-04T06:59:27Z | C6: gatesweep-66-g.jsonl | D6: 66-g | E6: exoj | F6: swept | G6: parts=26 OPEN=24 SOFT=0 HOLE=2 seal2x=5 missingLayers=[] fm=24
B7: 2026-10-04T06:59:27Z | C7: gatesweep-66-g.jsonl | D7: 66-g | E7: fleet-seeds | F7: swept | G7: parts=16 OPEN=15 SOFT=0 HOLE=1 seal2x=3 missingLayers=[0] fm=16
B8: 2026-10-04T06:59:27Z | C8: gatesweep-66-g.jsonl | D8: 66-g | E8: jev-garden | F8: swept | G8: parts=26 OPEN=26 SOFT=0 HOLE=0 seal2x=2 missingLayers=[] fm=26
B9: 2026-10-04T06:59:27Z | C9: gatesweep-66-g.jsonl | D9: 66-g | E9: jeviter | F9: swept | G9: parts=24 OPEN=24 SOFT=0 HOLE=0 seal2x=5 missingLayers=[] fm=24
B10: 2026-10-04T06:59:27Z | C10: gatesweep-66-g.jsonl | D10: 66-g | E10: cot-quilt | F10: swept | G10: parts=12 OPEN=9 SOFT=0 HOLE=3 seal2x=2 missingLayers=[] fm=12
B11: 2026-10-04T06:59:27Z | C11: gatesweep-66-g.jsonl | D11: 66-g | E11: MicroMoth-quilt | F11: swept | G11: parts=13 OPEN=10 SOFT=0 HOLE=3 seal2x=3 missingLayers=[] fm=13
B12: 2026-10-04T06:59:27Z | C12: gatesweep-66-g.jsonl | D12: 66-g | E12: moth-research | F12: swept | G12: parts=10 OPEN=6 SOFT=0 HOLE=4 seal2x=1 missingLayers=[] fm=10
B13: 2026-10-04T06:59:27Z | C13: gatesweep-66-g.jsonl | D13: 66-g | E13: quilt-dba | F13: swept | G13: parts=15 OPEN=15 SOFT=0 HOLE=0 seal2x=3 missingLayers=[] fm=15
B14: 2026-10-04T06:59:27Z | C14: gatesweep-66-g.jsonl | D14: 66-g | E14: quilt-quant | F14: swept | G14: parts=14 OPEN=13 SOFT=0 HOLE=1 seal2x=2 missingLayers=[] fm=14
B15: 2026-10-04T06:59:27Z | C15: gatesweep-66-g.jsonl | D15: 66-g | E15: quilt-raw | F15: swept | G15: parts=14 OPEN=12 SOFT=0 HOLE=2 seal2x=2 missingLayers=[2] fm=14
... B110: 2026-10-04T06:58:05Z | C110: parts-66-f.jsonl | D110: 66-f | E110: external-scouts | F110: smoke_recorded | G110: cmd="node -e \"JSON.parse each file in jev-garden/scouts/raw/*.json\"" verdict=PASS notes=All 5 raw scout JSONs parse: V-JEPA_2_JEPA_world_mode.json (4 results), test-time_training_layer.json (7), knowledge_distillation_L.json (7)

Sheet Sweep
B2: JEV gate sweep — pre-registered rules, aggregates, per-work verdicts
B4: rule | C4: decision (receipted before the run) | E4: work | F4: family | G4: OPEN | H4: SOFT | I4: HOLE | J4: missing_layers | K4: fm_parts | L4: prob_open | M4: smoke
B5: R1 OPEN | C5: gate non-empty AND gate_kind non-null -> emit(g=0.75, e=0.25, d=0.50) | E5: exoj | F5: garden | G5: 24 | H5: 0 | I5: 2 | J5: — | K5: 24 | L5: 0.631 | M5: PASS 3/3
B6: R2 SOFT | C6: gate non-empty AND gate_kind null -> emit(g=0.50, e=0.50, d=0.50) | E6: fleet-seeds | F6: garden | G6: 15 | H6: 0 | I6: 1 | J6: 0 | K6: 16 | L6: 0.6883 | M6: PASS (1 commit, SMOKE OK 3/3, tree clean after cleanup)
B7: R3 HOLE | C7: gate empty/null -> observe(d=0.20): explicit, recorded, LOCAL collapse | E7: jev-garden | F7: garden | G7: 26 | H7: 0 | I7: 0 | J7: — | K7: 26 | L7: 0.7996 | M7: PASS 30/30
B8: R4 SEAL | C8: gate_kind seal|conservation -> extra reinforcing emit(g=0.85, e=0.15, d=0.50) | E8: jeviter | F8: garden | G8: 24 | H8: 0 | I8: 0 | J8: — | K8: 24 | L8: 0.8523 | M8: PASS 85/85
B9: R5 LAYERHOLE | C9: work missing any layer 0-4 -> observe at that layer's cell | E9: cot-quilt | F9: labs | G9: 9 | H9: 0 | I9: 3 | J9: — | K9: 12 | L9: 0.8006 | M9: PASS (offline ritual: verdict CLEAN, exit 0) + live pipeline NOT_RUN
B10: R6 THIN | C10: work with <5 gated parts -> warning emit(g=0.35, e=0.65, d=0.50) | E10: MicroMoth-quilt | F10: labs | G10: 10 | H10: 0 | I10: 3 | J10: — | K10: 13 | L10: 0.766 | M10: PARTIAL (19 passed, 1 failed)
B11: geometry | C11: work i -> q=(i%7)-3 ; layer L -> r=L-2 ; radius 6 ; exoj policy=ledger | E11: moth-research | F11: labs | G11: 6 | H11: 0 | I11: 4 | J11: — | K11: 10 | L11: 0.7344 | M11: NOT_RUN (no executable entry point — docs-only research mooring)
B12: backend | C12: atlas-sweep: deterministic structural judgment; no LLM, no network | E12: quilt-dba | F12: labs | G12: 15 | H12: 0 | I12: 0 | J12: — | K12: 15 | L12: 0.7387 | M12: PASS (13/13 checks)
E13: quilt-quant | F13: labs | G13: 13 | H13: 0 | I13: 1 | J13: — | K13: 14 | L13: 0.717 | M13: PASS (17/17 checks green, 220ms, offline mode)
E14: quilt-raw | F14: labs | G14: 12 | H14: 0 | I14: 2 | J14: 2 | K14: 14 | L14: 0.661 | M14: PASS (18/18 checks sealed)
B15: gate_kind histogram (atlas totals) | E15: breakthrough-prospector | F15: meta | G15: 9 | H15: 0 | I15: 7 | J15: — | K15: 16 | L15: 0.5179 | M15: PASS
B16: gate_kind | C16: count | E16: craftmind-study | F16: meta | G16: 5 | H16: 0 | I16: 11 | J16: — | K16: 16 | L16: 0.4297 | M16: PASS
B17: invariant | C17: 100 | E17: external-scouts | F17: meta | G17: 5 | H17: 0 | I17: 12 | J17: — | K17: 17 | L17: 0.3726 | M17: PASS
B18: postcondition | C18: 87 | E18: quilt-atlas | F18: meta | G18: 6 | H18: 0 | I18: 6 | J18: — | K18: 12 | L18: 0.315 | M18: PASS
B19: admission | C19: 67 | E19: quilt-codespace | F19: meta | G19: 3 | H19: 0 | I19: 11 | J19: — | K19: 14 | L19: 0.2474 | M19: PASS
B20: seal | C20: 52 | E20: quilt-upstream | F20: meta | G20: 9 | H20: 0 | I20: 15 | J20: 3 | K20: 24 | L20: 0.1609 | M20: PASS
B21: precondition | C21: 50 | E21: si-fleet | F21: meta | G21: 8 | H21: 0 | I21: 8 | J21: — | K21: 16 | L21: 0.0698 | M21: PASS
B22: budget | C22: 25 | E22: superinstance-site | F22: meta | G22: 10 | H22: 0 | I22: 9 | J22: — | K22: 19 | L22: 0.067 | M22: PASS
B23: conservation | C23: 20 | E23: quilt-jev-toolkit | F23: organ | G23: 25 | H23: 0 | I23: 0 | J23: — | K23: 23 | L23: 0.086 | M23: PASS 44/44 (145ms) + boot-demo PASS + rewind-demo 7/7 stages PASS (all offline)
E24: quilt-mcp-receipts | F24: organ | G24: 16 | H24: 0 | I24: 0 | J24: — | K24: 11 | L24: 0.0949 | M24: PASS 15/15 (5.6s, offline)
E25: quilt-organ-workers | F25: organ | G25: 19 | H25: 0 | I25: 1 | J25: — | K25: 14 | L25: 0.1025 | M25: NOT_RUN
B26: layer histogram | E26: quilt-research-canons | F26: organ | G26: 9 | H26: 0 | I26: 5 | J26: — | K26: 4 | L26: 0.1031 | M26: PASS — 5/5 sprint scripts fully conform to the SPRINT-LINEAGE contract; 3/3 JSON artifacts parse
B27: layer | C27: parts | E27: jev-quilt | F27: substrate | G27: 18 | H27: 0 | I27: 2 | J27: — | K27: 11 | L27: 0.1132 | M27: PASS 249 ran, 0 failures (6 skipped, 2 expected failures) in 38.5s
B28: 0 substrate | C28: 75 | E28: qthe | F28: substrate | G28: 21 | H28: 0 | I28: 1 | J28: — | K28: 11 | L28: 0.1226 | M28: PASS 54/54
B29: 1 mechanism | C29: 170 | E29: quilt-jepa | F29: substrate | G29: 15 | H29: 0 | I29: 3 | J29: — | K29: 11 | L29: 0.1308 | M29: PASS (chain + seals)
B30: 2 policy | C30: 128 | E30: quilt-qcells | F30: substrate | G30: 20 | H30: 0 | I30: 1 | J30: — | K30: 13 | L30: 0.137 | M30: PASS — ALL GREEN, P1-P4 (16 circuits, 1418 rows, 4254/4254 tamper localized, 5/5 negatives, 6.4s)
B31: 3 interface | C31: 69 | E31: crab-traps | F31: swarm | G31: 16 | H31: 0 | I31: 6 | J31: — | K31: 20 | L31: 0.1329 | M31: 12/12 controls PASS, fail-closed (0.18s, stdlib-only, zero network)
B32: 4 evidence | C32: 86 | E32: quilt-murmur | F32: swarm | G32: 23 | H32: 0 | I32: 5 | J32: — | K32: 26 | L32: 0.1372 | M32: SMOKE OK — 16/16 checks pass
E33: quilt-pincher | F33: swarm | G33: 10 | H33: 0 | I33: 8 | J33: — | K33: 13 | L33: 0.14 | M33: 12/12 tests pass, 0 fail (5.2s, offline)
B35: chain of record
B36: deformations | C36: 474
B37: observations (collapses) | C37: 130
B38: prob_open at close | C38: 0.14
B39: zone at close | C39: 0.0571
B40: chain links | C40: 606
B41: chain verify ok | C41: True
B42: chain tip | C42: 13463fd02be3ac4fd18dce7c9c530d547fdda360b09d25999418b6b1301070b0

Sheet Review
B2: Review — live cross-checks
B4: check | C4: expected | D4: actual | E4: status
B5: Parts row count | C5: 528 | D5: =COUNTA(Parts!C5:C532) -> 528 | E5: =IF(C5=D5,"PASS","FAIL") -> PASS
B6: Gates row count = gated parts | C6: 401 | D6: =COUNTIFS(Parts!B5:B532,"<>",Parts!K5:K532,"<>") -> 401 | E6: =IF(C6=D6,"PASS","FAIL") -> PASS
B7: Gate-kind histogram sum | C7: 401 | D7: =SUM(Sweep!C17:C23) -> 401 | E7: =IF(C7=D7,"PASS","FAIL") -> PASS
B8: Layer histogram sum | C8: 528 | D8: =SUM(Sweep!C28:C32) -> 528 | E8: =IF(C8=D8,"PASS","FAIL") -> PASS
B9: Ideas row count | C9: 145 | D9: =COUNTA(Ideas!C5:C149) -> 145 | E9: =IF(C9=D9,"PASS","FAIL") -> PASS
B10: Cells row count | C10: 366 | D10: =COUNTA(Cells!C5:C370) -> 366 | E10: =IF(C10=D10,"PASS","FAIL") -> PASS
B11: Ledger row count | C11: 106 | D11: =COUNTA(Ledger!B5:B110) -> 106 | E11: =IF(C11=D11,"PASS","FAIL") -> PASS
B12: Corpus works rows | C12: 29 | D12: =COUNTA(Corpus!B5:B33) -> 29 | E12: =IF(C12=D12,"PASS","FAIL") -> PASS
